[
	{
		"C":"HH",
		"Y":2019,
		"N":886.8,
	},
	{
		"C":"HH",
		"Y":2020,
		"N":923.8,
	},
	{
		"C":"HH",
		"Y":2021,
		"N":984.0,
	},
	{
		"C":"HH",
		"Y":2022,
		"N":1050.0,
	},
	{
		"C":"HH",
		"Y":2023,
		"N":1119.0,
	},
	{
		"C":"HH",
		"Y":2024,
		"N":1188.6,
	},
	{
		"C":"HH",
		"Y":2025,
		"N":1255.5,
	},
	{
		"C":"HH",
		"Y":2026,
		"N":1320.7,
	},
	{
		"C":"HH",
		"Y":2027,
		"N":1383.3,
	},
	{
		"C":"HH",
		"Y":2028,
		"N":1443.0,
	},
	{
		"C":"HH",
		"Y":2029,
		"N":1500.0,
	},
	{
		"C":"HH",
		"Y":2030,
		"N":1549.6000000000001,
	},
	{
		"C":"HH",
		"Y":2031,
		"N":1599.7,
	},
	{
		"C":"HH",
		"Y":2032,
		"N":1649.1000000000001,
	},
	{
		"C":"HH",
		"Y":2033,
		"N":1698.4,
	},
	{
		"C":"HH",
		"Y":2034,
		"N":1747.6,
	},
	{
		"C":"HH",
		"Y":2035,
		"N":1795.3,
	},
	{
		"C":"HH",
		"Y":2036,
		"N":1842.8,
	},
	{
		"C":"HH",
		"Y":2037,
		"N":1888.7,
	},
	{
		"C":"HH",
		"Y":2038,
		"N":1932.9,
	},
	{
		"C":"HH",
		"Y":2039,
		"N":1976.6,
	},
	{
		"C":"HH",
		"Y":2040,
		"N":2017.9,
	},
	{
		"C":"HH",
		"Y":2041,
		"N":2065.1,
	},
	{
		"C":"HH",
		"Y":2042,
		"N":2110.2,
	},
	{
		"C":"HH",
		"Y":2043,
		"N":2154.4,
	},
	{
		"C":"HH",
		"Y":2044,
		"N":2197.7,
	},
	{
		"C":"HH",
		"Y":2045,
		"N":2240.4,
	},
	{
		"C":"HH",
		"Y":2046,
		"N":2284.4,
	},
	{
		"C":"HH",
		"Y":2047,
		"N":2327.3,
	},
	{
		"C":"HH",
		"Y":2048,
		"N":2369.8,
	},
	{
		"C":"HH",
		"Y":2049,
		"N":2413.7,
	},
	{
		"C":"HH",
		"Y":2050,
		"N":2456.7,
	},
	{
		"C":"POP",
		"Y":2019,
		"N":2727.7,
	},
	{
		"C":"POP",
		"Y":2020,
		"N":2835.0,
	},
	{
		"C":"POP",
		"Y":2021,
		"N":2999.5,
	},
	{
		"C":"POP",
		"Y":2022,
		"N":3181.2,
	},
	{
		"C":"POP",
		"Y":2023,
		"N":3372.3,
	},
	{
		"C":"POP",
		"Y":2024,
		"N":3562.7,
	},
	{
		"C":"POP",
		"Y":2025,
		"N":3744.5,
	},
	{
		"C":"POP",
		"Y":2026,
		"N":3920.0,
	},
	{
		"C":"POP",
		"Y":2027,
		"N":4086.2,
	},
	{
		"C":"POP",
		"Y":2028,
		"N":4240.6,
	},
	{
		"C":"POP",
		"Y":2029,
		"N":4384.9,
	},
	{
		"C":"POP",
		"Y":2030,
		"N":4504.4,
	},
	{
		"C":"POP",
		"Y":2031,
		"N":4626.4,
	},
	{
		"C":"POP",
		"Y":2032,
		"N":4746.1,
	},
	{
		"C":"POP",
		"Y":2033,
		"N":4863.7,
	},
	{
		"C":"POP",
		"Y":2034,
		"N":4979.3,
	},
	{
		"C":"POP",
		"Y":2035,
		"N":5091.6,
	},
	{
		"C":"POP",
		"Y":2036,
		"N":5205.4,
	},
	{
		"C":"POP",
		"Y":2037,
		"N":5317.5,
	},
	{
		"C":"POP",
		"Y":2038,
		"N":5425.8,
	},
	{
		"C":"POP",
		"Y":2039,
		"N":5532.8,
	},
	{
		"C":"POP",
		"Y":2040,
		"N":5633.3,
	},
	{
		"C":"POP",
		"Y":2041,
		"N":5732.7,
	},
	{
		"C":"POP",
		"Y":2042,
		"N":5827.8,
	},
	{
		"C":"POP",
		"Y":2043,
		"N":5920.9,
	},
	{
		"C":"POP",
		"Y":2044,
		"N":6010.2,
	},
	{
		"C":"POP",
		"Y":2045,
		"N":6096.0,
	},
	{
		"C":"POP",
		"Y":2046,
		"N":6182.4,
	},
	{
		"C":"POP",
		"Y":2047,
		"N":6265.5,
	},
	{
		"C":"POP",
		"Y":2048,
		"N":6348.1,
	},
	{
		"C":"POP",
		"Y":2049,
		"N":6433.1,
	},
	{
		"C":"POP",
		"Y":2050,
		"N":6514.3,
	},
	{
		"C":"AEMP",
		"Y":2019,
		"N":821.6999999999999,
	},
	{
		"C":"AEMP",
		"Y":2020,
		"N":876.0,
	},
	{
		"C":"AEMP",
		"Y":2021,
		"N":960.3,
	},
	{
		"C":"AEMP",
		"Y":2022,
		"N":987.9,
	},
	{
		"C":"AEMP",
		"Y":2023,
		"N":1027.1000000000001,
	},
	{
		"C":"AEMP",
		"Y":2024,
		"N":1069.8,
	},
	{
		"C":"AEMP",
		"Y":2025,
		"N":1089.2,
	},
	{
		"C":"AEMP",
		"Y":2026,
		"N":1121.0,
	},
	{
		"C":"AEMP",
		"Y":2027,
		"N":1148.3,
	},
	{
		"C":"AEMP",
		"Y":2028,
		"N":1173.4,
	},
	{
		"C":"AEMP",
		"Y":2029,
		"N":1201.3,
	},
	{
		"C":"AEMP",
		"Y":2030,
		"N":1202.0,
	},
	{
		"C":"AEMP",
		"Y":2031,
		"N":1241.1,
	},
	{
		"C":"AEMP",
		"Y":2032,
		"N":1267.9,
	},
	{
		"C":"AEMP",
		"Y":2033,
		"N":1289.8999999999999,
	},
	{
		"C":"AEMP",
		"Y":2034,
		"N":1315.7,
	},
	{
		"C":"AEMP",
		"Y":2035,
		"N":1332.8999999999999,
	},
	{
		"C":"AEMP",
		"Y":2036,
		"N":1360.1000000000001,
	},
	{
		"C":"AEMP",
		"Y":2037,
		"N":1383.4,
	},
	{
		"C":"AEMP",
		"Y":2038,
		"N":1405.4,
	},
	{
		"C":"AEMP",
		"Y":2039,
		"N":1426.6,
	},
	{
		"C":"AEMP",
		"Y":2040,
		"N":1439.8999999999999,
	},
	{
		"C":"AEMP",
		"Y":2041,
		"N":1468.5,
	},
	{
		"C":"AEMP",
		"Y":2042,
		"N":1486.5,
	},
	{
		"C":"AEMP",
		"Y":2043,
		"N":1505.8,
	},
	{
		"C":"AEMP",
		"Y":2044,
		"N":1523.9,
	},
	{
		"C":"AEMP",
		"Y":2045,
		"N":1540.0,
	},
	{
		"C":"AEMP",
		"Y":2046,
		"N":1563.5,
	},
	{
		"C":"AEMP",
		"Y":2047,
		"N":1575.9,
	},
	{
		"C":"AEMP",
		"Y":2048,
		"N":1593.7,
	},
	{
		"C":"AEMP",
		"Y":2049,
		"N":1617.5,
	},
	{
		"C":"AEMP",
		"Y":2050,
		"N":1625.2,
	},
	{
		"C":"RTL",
		"Y":2019,
		"N":188.5,
	},
	{
		"C":"RTL",
		"Y":2020,
		"N":166.0,
	},
	{
		"C":"RTL",
		"Y":2021,
		"N":190.6,
	},
	{
		"C":"RTL",
		"Y":2022,
		"N":187.2,
	},
	{
		"C":"RTL",
		"Y":2023,
		"N":192.9,
	},
	{
		"C":"RTL",
		"Y":2024,
		"N":196.5,
	},
	{
		"C":"RTL",
		"Y":2025,
		"N":199.0,
	},
	{
		"C":"RTL",
		"Y":2026,
		"N":202.3,
	},
	{
		"C":"RTL",
		"Y":2027,
		"N":205.4,
	},
	{
		"C":"RTL",
		"Y":2028,
		"N":208.6,
	},
	{
		"C":"RTL",
		"Y":2029,
		"N":212.5,
	},
	{
		"C":"RTL",
		"Y":2030,
		"N":216.39999999999998,
	},
	{
		"C":"RTL",
		"Y":2031,
		"N":221.0,
	},
	{
		"C":"RTL",
		"Y":2032,
		"N":225.0,
	},
	{
		"C":"RTL",
		"Y":2033,
		"N":229.5,
	},
	{
		"C":"RTL",
		"Y":2034,
		"N":233.7,
	},
	{
		"C":"RTL",
		"Y":2035,
		"N":238.20000000000002,
	},
	{
		"C":"RTL",
		"Y":2036,
		"N":242.7,
	},
	{
		"C":"RTL",
		"Y":2037,
		"N":247.5,
	},
	{
		"C":"RTL",
		"Y":2038,
		"N":250.8,
	},
	{
		"C":"RTL",
		"Y":2039,
		"N":254.5,
	},
	{
		"C":"RTL",
		"Y":2040,
		"N":258.0,
	},
	{
		"C":"RTL",
		"Y":2041,
		"N":262.6,
	},
	{
		"C":"RTL",
		"Y":2042,
		"N":266.2,
	},
	{
		"C":"RTL",
		"Y":2043,
		"N":270.5,
	},
	{
		"C":"RTL",
		"Y":2044,
		"N":274.6,
	},
	{
		"C":"RTL",
		"Y":2045,
		"N":278.8,
	},
	{
		"C":"RTL",
		"Y":2046,
		"N":282.8,
	},
	{
		"C":"RTL",
		"Y":2047,
		"N":287.6,
	},
	{
		"C":"RTL",
		"Y":2048,
		"N":292.4,
	},
	{
		"C":"RTL",
		"Y":2049,
		"N":296.5,
	},
	{
		"C":"RTL",
		"Y":2050,
		"N":300.1,
	},
	{
		"C":"IND",
		"Y":2019,
		"N":22.8,
	},
	{
		"C":"IND",
		"Y":2020,
		"N":19.4,
	},
	{
		"C":"IND",
		"Y":2021,
		"N":28.7,
	},
	{
		"C":"IND",
		"Y":2022,
		"N":31.3,
	},
	{
		"C":"IND",
		"Y":2023,
		"N":35.3,
	},
	{
		"C":"IND",
		"Y":2024,
		"N":38.7,
	},
	{
		"C":"IND",
		"Y":2025,
		"N":42.300000000000004,
	},
	{
		"C":"IND",
		"Y":2026,
		"N":45.0,
	},
	{
		"C":"IND",
		"Y":2027,
		"N":47.6,
	},
	{
		"C":"IND",
		"Y":2028,
		"N":49.800000000000004,
	},
	{
		"C":"IND",
		"Y":2029,
		"N":51.6,
	},
	{
		"C":"IND",
		"Y":2030,
		"N":53.4,
	},
	{
		"C":"IND",
		"Y":2031,
		"N":55.1,
	},
	{
		"C":"IND",
		"Y":2032,
		"N":56.5,
	},
	{
		"C":"IND",
		"Y":2033,
		"N":58.0,
	},
	{
		"C":"IND",
		"Y":2034,
		"N":59.5,
	},
	{
		"C":"IND",
		"Y":2035,
		"N":60.5,
	},
	{
		"C":"IND",
		"Y":2036,
		"N":61.4,
	},
	{
		"C":"IND",
		"Y":2037,
		"N":62.2,
	},
	{
		"C":"IND",
		"Y":2038,
		"N":63.1,
	},
	{
		"C":"IND",
		"Y":2039,
		"N":63.7,
	},
	{
		"C":"IND",
		"Y":2040,
		"N":64.4,
	},
	{
		"C":"IND",
		"Y":2041,
		"N":65.0,
	},
	{
		"C":"IND",
		"Y":2042,
		"N":65.8,
	},
	{
		"C":"IND",
		"Y":2043,
		"N":66.5,
	},
	{
		"C":"IND",
		"Y":2044,
		"N":67.1,
	},
	{
		"C":"IND",
		"Y":2045,
		"N":68.0,
	},
	{
		"C":"IND",
		"Y":2046,
		"N":68.4,
	},
	{
		"C":"IND",
		"Y":2047,
		"N":68.5,
	},
	{
		"C":"IND",
		"Y":2048,
		"N":68.9,
	},
	{
		"C":"IND",
		"Y":2049,
		"N":69.3,
	},
	{
		"C":"IND",
		"Y":2050,
		"N":69.3,
	},
	{
		"C":"OTHR",
		"Y":2019,
		"N":345.0,
	},
	{
		"C":"OTHR",
		"Y":2020,
		"N":338.09999999999997,
	},
	{
		"C":"OTHR",
		"Y":2021,
		"N":372.9,
	},
	{
		"C":"OTHR",
		"Y":2022,
		"N":392.20000000000005,
	},
	{
		"C":"OTHR",
		"Y":2023,
		"N":413.7,
	},
	{
		"C":"OTHR",
		"Y":2024,
		"N":432.90000000000003,
	},
	{
		"C":"OTHR",
		"Y":2025,
		"N":448.8,
	},
	{
		"C":"OTHR",
		"Y":2026,
		"N":464.2,
	},
	{
		"C":"OTHR",
		"Y":2027,
		"N":478.90000000000003,
	},
	{
		"C":"OTHR",
		"Y":2028,
		"N":493.9,
	},
	{
		"C":"OTHR",
		"Y":2029,
		"N":507.7,
	},
	{
		"C":"OTHR",
		"Y":2030,
		"N":520.6,
	},
	{
		"C":"OTHR",
		"Y":2031,
		"N":532.6,
	},
	{
		"C":"OTHR",
		"Y":2032,
		"N":544.6,
	},
	{
		"C":"OTHR",
		"Y":2033,
		"N":556.2,
	},
	{
		"C":"OTHR",
		"Y":2034,
		"N":567.1,
	},
	{
		"C":"OTHR",
		"Y":2035,
		"N":577.9,
	},
	{
		"C":"OTHR",
		"Y":2036,
		"N":588.8,
	},
	{
		"C":"OTHR",
		"Y":2037,
		"N":598.9,
	},
	{
		"C":"OTHR",
		"Y":2038,
		"N":609.6,
	},
	{
		"C":"OTHR",
		"Y":2039,
		"N":619.2,
	},
	{
		"C":"OTHR",
		"Y":2040,
		"N":629.7,
	},
	{
		"C":"OTHR",
		"Y":2041,
		"N":638.6,
	},
	{
		"C":"OTHR",
		"Y":2042,
		"N":647.0,
	},
	{
		"C":"OTHR",
		"Y":2043,
		"N":655.2,
	},
	{
		"C":"OTHR",
		"Y":2044,
		"N":662.9,
	},
	{
		"C":"OTHR",
		"Y":2045,
		"N":669.7,
	},
	{
		"C":"OTHR",
		"Y":2046,
		"N":677.0,
	},
	{
		"C":"OTHR",
		"Y":2047,
		"N":683.4,
	},
	{
		"C":"OTHR",
		"Y":2048,
		"N":689.4,
	},
	{
		"C":"OTHR",
		"Y":2049,
		"N":695.1,
	},
	{
		"C":"OTHR",
		"Y":2050,
		"N":701.5999999999999,
	},
	{
		"C":"TPCL",
		"Y":2019,
		"N":556.3,
	},
	{
		"C":"TPCL",
		"Y":2020,
		"N":523.5,
	},
	{
		"C":"TPCL",
		"Y":2021,
		"N":592.2,
	},
	{
		"C":"TPCL",
		"Y":2022,
		"N":610.7,
	},
	{
		"C":"TPCL",
		"Y":2023,
		"N":641.9,
	},
	{
		"C":"TPCL",
		"Y":2024,
		"N":668.1,
	},
	{
		"C":"TPCL",
		"Y":2025,
		"N":690.1,
	},
	{
		"C":"TPCL",
		"Y":2026,
		"N":711.5,
	},
	{
		"C":"TPCL",
		"Y":2027,
		"N":731.9,
	},
	{
		"C":"TPCL",
		"Y":2028,
		"N":752.3,
	},
	{
		"C":"TPCL",
		"Y":2029,
		"N":771.8,
	},
	{
		"C":"TPCL",
		"Y":2030,
		"N":790.4,
	},
	{
		"C":"TPCL",
		"Y":2031,
		"N":808.7,
	},
	{
		"C":"TPCL",
		"Y":2032,
		"N":826.1,
	},
	{
		"C":"TPCL",
		"Y":2033,
		"N":843.7,
	},
	{
		"C":"TPCL",
		"Y":2034,
		"N":860.3,
	},
	{
		"C":"TPCL",
		"Y":2035,
		"N":876.6,
	},
	{
		"C":"TPCL",
		"Y":2036,
		"N":892.9,
	},
	{
		"C":"TPCL",
		"Y":2037,
		"N":908.6,
	},
	{
		"C":"TPCL",
		"Y":2038,
		"N":923.5,
	},
	{
		"C":"TPCL",
		"Y":2039,
		"N":937.4,
	},
	{
		"C":"TPCL",
		"Y":2040,
		"N":952.1,
	},
	{
		"C":"TPCL",
		"Y":2041,
		"N":966.2,
	},
	{
		"C":"TPCL",
		"Y":2042,
		"N":979.0,
	},
	{
		"C":"TPCL",
		"Y":2043,
		"N":992.2,
	},
	{
		"C":"TPCL",
		"Y":2044,
		"N":1004.6,
	},
	{
		"C":"TPCL",
		"Y":2045,
		"N":1016.5,
	},
	{
		"C":"TPCL",
		"Y":2046,
		"N":1028.2,
	},
	{
		"C":"TPCL",
		"Y":2047,
		"N":1039.5,
	},
	{
		"C":"TPCL",
		"Y":2048,
		"N":1050.7,
	},
	{
		"C":"TPCL",
		"Y":2049,
		"N":1060.9,
	},
	{
		"C":"TPCL",
		"Y":2050,
		"N":1071.0,
	},
	{
		"C":"HJI",
		"Y":2019,
		"N":2152.54,
	},
	{
		"C":"HJI",
		"Y":2020,
		"N":2186.34,
	},
	{
		"C":"HJI",
		"Y":2021,
		"N":2363.4,
	},
	{
		"C":"HJI",
		"Y":2022,
		"N":2500.7,
	},
	{
		"C":"HJI",
		"Y":2023,
		"N":2656.1,
	},
	{
		"C":"HJI",
		"Y":2024,
		"N":2807.58,
	},
	{
		"C":"HJI",
		"Y":2025,
		"N":2950.0,
	},
	{
		"C":"HJI",
		"Y":2026,
		"N":3088.76,
	},
	{
		"C":"HJI",
		"Y":2027,
		"N":3221.84,
	},
	{
		"C":"HJI",
		"Y":2028,
		"N":3349.7,
	},
	{
		"C":"HJI",
		"Y":2029,
		"N":3471.8,
	},
	{
		"C":"HJI",
		"Y":2030,
		"N":3579.68,
	},
	{
		"C":"HJI",
		"Y":2031,
		"N":3688.16,
	},
	{
		"C":"HJI",
		"Y":2032,
		"N":3794.48,
	},
	{
		"C":"HJI",
		"Y":2033,
		"N":3900.82,
	},
	{
		"C":"HJI",
		"Y":2034,
		"N":4005.98,
	},
	{
		"C":"HJI",
		"Y":2035,
		"N":4108.14,
	},
	{
		"C":"HJI",
		"Y":2036,
		"N":4209.94,
	},
	{
		"C":"HJI",
		"Y":2037,
		"N":4308.26,
	},
	{
		"C":"HJI",
		"Y":2038,
		"N":4402.72,
	},
	{
		"C":"HJI",
		"Y":2039,
		"N":4495.28,
	},
	{
		"C":"HJI",
		"Y":2040,
		"N":4584.32,
	},
	{
		"C":"HJI",
		"Y":2041,
		"N":4683.38,
	},
	{
		"C":"HJI",
		"Y":2042,
		"N":4777.36,
	},
	{
		"C":"HJI",
		"Y":2043,
		"N":4870.12,
	},
	{
		"C":"HJI",
		"Y":2044,
		"N":4960.46,
	},
	{
		"C":"HJI",
		"Y":2045,
		"N":5049.22,
	},
	{
		"C":"HJI",
		"Y":2046,
		"N":5140.12,
	},
	{
		"C":"HJI",
		"Y":2047,
		"N":5228.639999999999,
	},
	{
		"C":"HJI",
		"Y":2048,
		"N":5316.34,
	},
	{
		"C":"HJI",
		"Y":2049,
		"N":5405.56,
	},
	{
		"C":"HJI",
		"Y":2050,
		"N":5493.0599999999995,
	}
]
