[
	{
		"C":"HH",
		"Y":2019,
		"N":2210.29,
	},
	{
		"C":"HH",
		"Y":2020,
		"N":2252.6,
	},
	{
		"C":"HH",
		"Y":2021,
		"N":2311.4,
	},
	{
		"C":"HH",
		"Y":2022,
		"N":2369.8,
	},
	{
		"C":"HH",
		"Y":2023,
		"N":2431.3,
	},
	{
		"C":"HH",
		"Y":2024,
		"N":2371.4,
	},
	{
		"C":"HH",
		"Y":2025,
		"N":2554.2,
	},
	{
		"C":"HH",
		"Y":2026,
		"N":2612.7,
	},
	{
		"C":"HH",
		"Y":2027,
		"N":2668.6,
	},
	{
		"C":"HH",
		"Y":2028,
		"N":2719.3,
	},
	{
		"C":"HH",
		"Y":2029,
		"N":2767.8,
	},
	{
		"C":"HH",
		"Y":2030,
		"N":2814.4,
	},
	{
		"C":"HH",
		"Y":2031,
		"N":2860.5,
	},
	{
		"C":"HH",
		"Y":2032,
		"N":2906.6,
	},
	{
		"C":"HH",
		"Y":2033,
		"N":2953.3,
	},
	{
		"C":"HH",
		"Y":2034,
		"N":2998.4,
	},
	{
		"C":"HH",
		"Y":2035,
		"N":3043.1,
	},
	{
		"C":"HH",
		"Y":2036,
		"N":3087.8,
	},
	{
		"C":"HH",
		"Y":2037,
		"N":3131.2,
	},
	{
		"C":"HH",
		"Y":2038,
		"N":3173.8,
	},
	{
		"C":"HH",
		"Y":2039,
		"N":3215.4,
	},
	{
		"C":"HH",
		"Y":2040,
		"N":3253.5,
	},
	{
		"C":"HH",
		"Y":2041,
		"N":3336.2999999999997,
	},
	{
		"C":"HH",
		"Y":2042,
		"N":3416.5,
	},
	{
		"C":"HH",
		"Y":2043,
		"N":3493.5,
	},
	{
		"C":"HH",
		"Y":2044,
		"N":3569.5,
	},
	{
		"C":"HH",
		"Y":2045,
		"N":3644.9,
	},
	{
		"C":"HH",
		"Y":2046,
		"N":3718.3,
	},
	{
		"C":"HH",
		"Y":2047,
		"N":3791.4,
	},
	{
		"C":"HH",
		"Y":2048,
		"N":3862.4,
	},
	{
		"C":"HH",
		"Y":2049,
		"N":3933.0,
	},
	{
		"C":"HH",
		"Y":2050,
		"N":4002.1,
	},
	{
		"C":"POP",
		"Y":2019,
		"N":7033.49,
	},
	{
		"C":"POP",
		"Y":2020,
		"N":7161.2,
	},
	{
		"C":"POP",
		"Y":2021,
		"N":7295.3,
	},
	{
		"C":"POP",
		"Y":2022,
		"N":7412.1,
	},
	{
		"C":"POP",
		"Y":2023,
		"N":7536.2,
	},
	{
		"C":"POP",
		"Y":2024,
		"N":7227.9,
	},
	{
		"C":"POP",
		"Y":2025,
		"N":7782.8,
	},
	{
		"C":"POP",
		"Y":2026,
		"N":7896.400000000001,
	},
	{
		"C":"POP",
		"Y":2027,
		"N":7999.9,
	},
	{
		"C":"POP",
		"Y":2028,
		"N":8094.400000000001,
	},
	{
		"C":"POP",
		"Y":2029,
		"N":8179.9,
	},
	{
		"C":"POP",
		"Y":2030,
		"N":8259.6,
	},
	{
		"C":"POP",
		"Y":2031,
		"N":8344.9,
	},
	{
		"C":"POP",
		"Y":2032,
		"N":8432.1,
	},
	{
		"C":"POP",
		"Y":2033,
		"N":8521.6,
	},
	{
		"C":"POP",
		"Y":2034,
		"N":8612.5,
	},
	{
		"C":"POP",
		"Y":2035,
		"N":8703.2,
	},
	{
		"C":"POP",
		"Y":2036,
		"N":8793.6,
	},
	{
		"C":"POP",
		"Y":2037,
		"N":8884.0,
	},
	{
		"C":"POP",
		"Y":2038,
		"N":8973.5,
	},
	{
		"C":"POP",
		"Y":2039,
		"N":9061.8,
	},
	{
		"C":"POP",
		"Y":2040,
		"N":9147.0,
	},
	{
		"C":"POP",
		"Y":2041,
		"N":9342.8,
	},
	{
		"C":"POP",
		"Y":2042,
		"N":9536.5,
	},
	{
		"C":"POP",
		"Y":2043,
		"N":9730.2,
	},
	{
		"C":"POP",
		"Y":2044,
		"N":9919.3,
	},
	{
		"C":"POP",
		"Y":2045,
		"N":10106.9,
	},
	{
		"C":"POP",
		"Y":2046,
		"N":10294.7,
	},
	{
		"C":"POP",
		"Y":2047,
		"N":10479.4,
	},
	{
		"C":"POP",
		"Y":2048,
		"N":10661.6,
	},
	{
		"C":"POP",
		"Y":2049,
		"N":10842.6,
	},
	{
		"C":"POP",
		"Y":2050,
		"N":11021.3,
	},
	{
		"C":"AEMP",
		"Y":2019,
		"N":3505.9,
	},
	{
		"C":"AEMP",
		"Y":2020,
		"N":3671.3,
	},
	{
		"C":"AEMP",
		"Y":2021,
		"N":3632.2,
	},
	{
		"C":"AEMP",
		"Y":2022,
		"N":3636.8,
	},
	{
		"C":"AEMP",
		"Y":2023,
		"N":3718.4,
	},
	{
		"C":"AEMP",
		"Y":2024,
		"N":135.2,
	},
	{
		"C":"AEMP",
		"Y":2025,
		"N":3818.9,
	},
	{
		"C":"AEMP",
		"Y":2026,
		"N":3846.8,
	},
	{
		"C":"AEMP",
		"Y":2027,
		"N":3875.5,
	},
	{
		"C":"AEMP",
		"Y":2028,
		"N":3904.4,
	},
	{
		"C":"AEMP",
		"Y":2029,
		"N":3946.6,
	},
	{
		"C":"AEMP",
		"Y":2030,
		"N":3983.9,
	},
	{
		"C":"AEMP",
		"Y":2031,
		"N":4017.2,
	},
	{
		"C":"AEMP",
		"Y":2032,
		"N":4055.4,
	},
	{
		"C":"AEMP",
		"Y":2033,
		"N":4095.9,
	},
	{
		"C":"AEMP",
		"Y":2034,
		"N":4137.3,
	},
	{
		"C":"AEMP",
		"Y":2035,
		"N":4177.2,
	},
	{
		"C":"AEMP",
		"Y":2036,
		"N":4215.5,
	},
	{
		"C":"AEMP",
		"Y":2037,
		"N":4254.2,
	},
	{
		"C":"AEMP",
		"Y":2038,
		"N":4294.2,
	},
	{
		"C":"AEMP",
		"Y":2039,
		"N":4325.5,
	},
	{
		"C":"AEMP",
		"Y":2040,
		"N":4354.8,
	},
	{
		"C":"AEMP",
		"Y":2041,
		"N":4658.7,
	},
	{
		"C":"AEMP",
		"Y":2042,
		"N":4716.2,
	},
	{
		"C":"AEMP",
		"Y":2043,
		"N":4772.2,
	},
	{
		"C":"AEMP",
		"Y":2044,
		"N":4829.6,
	},
	{
		"C":"AEMP",
		"Y":2045,
		"N":4880.9,
	},
	{
		"C":"AEMP",
		"Y":2046,
		"N":4942.7,
	},
	{
		"C":"AEMP",
		"Y":2047,
		"N":4997.3,
	},
	{
		"C":"AEMP",
		"Y":2048,
		"N":5044.6,
	},
	{
		"C":"AEMP",
		"Y":2049,
		"N":5100.1,
	},
	{
		"C":"AEMP",
		"Y":2050,
		"N":5147.8,
	},
	{
		"C":"RTL",
		"Y":2019,
		"N":159.92,
	},
	{
		"C":"RTL",
		"Y":2020,
		"N":157.29999999999998,
	},
	{
		"C":"RTL",
		"Y":2021,
		"N":184.5,
	},
	{
		"C":"RTL",
		"Y":2022,
		"N":187.20000000000002,
	},
	{
		"C":"RTL",
		"Y":2023,
		"N":193.1,
	},
	{
		"C":"RTL",
		"Y":2024,
		"N":552.4,
	},
	{
		"C":"RTL",
		"Y":2025,
		"N":199.5,
	},
	{
		"C":"RTL",
		"Y":2026,
		"N":201.5,
	},
	{
		"C":"RTL",
		"Y":2027,
		"N":202.7,
	},
	{
		"C":"RTL",
		"Y":2028,
		"N":205.5,
	},
	{
		"C":"RTL",
		"Y":2029,
		"N":209.4,
	},
	{
		"C":"RTL",
		"Y":2030,
		"N":214.6,
	},
	{
		"C":"RTL",
		"Y":2031,
		"N":216.8,
	},
	{
		"C":"RTL",
		"Y":2032,
		"N":222.1,
	},
	{
		"C":"RTL",
		"Y":2033,
		"N":226.7,
	},
	{
		"C":"RTL",
		"Y":2034,
		"N":231.7,
	},
	{
		"C":"RTL",
		"Y":2035,
		"N":237.1,
	},
	{
		"C":"RTL",
		"Y":2036,
		"N":242.1,
	},
	{
		"C":"RTL",
		"Y":2037,
		"N":247.70000000000002,
	},
	{
		"C":"RTL",
		"Y":2038,
		"N":252.2,
	},
	{
		"C":"RTL",
		"Y":2039,
		"N":256.9,
	},
	{
		"C":"RTL",
		"Y":2040,
		"N":261.9,
	},
	{
		"C":"RTL",
		"Y":2041,
		"N":267.4,
	},
	{
		"C":"RTL",
		"Y":2042,
		"N":272.59999999999997,
	},
	{
		"C":"RTL",
		"Y":2043,
		"N":278.2,
	},
	{
		"C":"RTL",
		"Y":2044,
		"N":282.5,
	},
	{
		"C":"RTL",
		"Y":2045,
		"N":288.5,
	},
	{
		"C":"RTL",
		"Y":2046,
		"N":293.8,
	},
	{
		"C":"RTL",
		"Y":2047,
		"N":300.40000000000003,
	},
	{
		"C":"RTL",
		"Y":2048,
		"N":306.1,
	},
	{
		"C":"RTL",
		"Y":2049,
		"N":312.1,
	},
	{
		"C":"RTL",
		"Y":2050,
		"N":316.7,
	},
	{
		"C":"IND",
		"Y":2019,
		"N":1386.23,
	},
	{
		"C":"IND",
		"Y":2020,
		"N":1364.3,
	},
	{
		"C":"IND",
		"Y":2021,
		"N":1386.2,
	},
	{
		"C":"IND",
		"Y":2022,
		"N":1389.0,
	},
	{
		"C":"IND",
		"Y":2023,
		"N":1402.7,
	},
	{
		"C":"IND",
		"Y":2024,
		"N":392.4,
	},
	{
		"C":"IND",
		"Y":2025,
		"N":1417.2,
	},
	{
		"C":"IND",
		"Y":2026,
		"N":1423.6,
	},
	{
		"C":"IND",
		"Y":2027,
		"N":1429.0,
	},
	{
		"C":"IND",
		"Y":2028,
		"N":1432.8999999999999,
	},
	{
		"C":"IND",
		"Y":2029,
		"N":1439.6,
	},
	{
		"C":"IND",
		"Y":2030,
		"N":1446.4,
	},
	{
		"C":"IND",
		"Y":2031,
		"N":1453.0,
	},
	{
		"C":"IND",
		"Y":2032,
		"N":1459.3,
	},
	{
		"C":"IND",
		"Y":2033,
		"N":1466.7,
	},
	{
		"C":"IND",
		"Y":2034,
		"N":1474.2,
	},
	{
		"C":"IND",
		"Y":2035,
		"N":1474.6000000000001,
	},
	{
		"C":"IND",
		"Y":2036,
		"N":1475.2,
	},
	{
		"C":"IND",
		"Y":2037,
		"N":1476.0,
	},
	{
		"C":"IND",
		"Y":2038,
		"N":1476.9,
	},
	{
		"C":"IND",
		"Y":2039,
		"N":1477.7,
	},
	{
		"C":"IND",
		"Y":2040,
		"N":1477.2,
	},
	{
		"C":"IND",
		"Y":2041,
		"N":1475.8999999999999,
	},
	{
		"C":"IND",
		"Y":2042,
		"N":1478.5,
	},
	{
		"C":"IND",
		"Y":2043,
		"N":1480.3,
	},
	{
		"C":"IND",
		"Y":2044,
		"N":1481.7,
	},
	{
		"C":"IND",
		"Y":2045,
		"N":1483.6,
	},
	{
		"C":"IND",
		"Y":2046,
		"N":1482.6,
	},
	{
		"C":"IND",
		"Y":2047,
		"N":1478.9,
	},
	{
		"C":"IND",
		"Y":2048,
		"N":1475.2,
	},
	{
		"C":"IND",
		"Y":2049,
		"N":1471.5,
	},
	{
		"C":"IND",
		"Y":2050,
		"N":1466.3,
	},
	{
		"C":"OTHR",
		"Y":2019,
		"N":966.38,
	},
	{
		"C":"OTHR",
		"Y":2020,
		"N":929.7,
	},
	{
		"C":"OTHR",
		"Y":2021,
		"N":1020.5,
	},
	{
		"C":"OTHR",
		"Y":2022,
		"N":1079.7,
	},
	{
		"C":"OTHR",
		"Y":2023,
		"N":1119.2,
	},
	{
		"C":"OTHR",
		"Y":2024,
		"N":859.2,
	},
	{
		"C":"OTHR",
		"Y":2025,
		"N":1167.6,
	},
	{
		"C":"OTHR",
		"Y":2026,
		"N":1184.1,
	},
	{
		"C":"OTHR",
		"Y":2027,
		"N":1197.8,
	},
	{
		"C":"OTHR",
		"Y":2028,
		"N":1217.2,
	},
	{
		"C":"OTHR",
		"Y":2029,
		"N":1239.0,
	},
	{
		"C":"OTHR",
		"Y":2030,
		"N":1256.1000000000001,
	},
	{
		"C":"OTHR",
		"Y":2031,
		"N":1266.8,
	},
	{
		"C":"OTHR",
		"Y":2032,
		"N":1282.3,
	},
	{
		"C":"OTHR",
		"Y":2033,
		"N":1296.6,
	},
	{
		"C":"OTHR",
		"Y":2034,
		"N":1315.8,
	},
	{
		"C":"OTHR",
		"Y":2035,
		"N":1334.9,
	},
	{
		"C":"OTHR",
		"Y":2036,
		"N":1354.8,
	},
	{
		"C":"OTHR",
		"Y":2037,
		"N":1374.6,
	},
	{
		"C":"OTHR",
		"Y":2038,
		"N":1392.4,
	},
	{
		"C":"OTHR",
		"Y":2039,
		"N":1410.0,
	},
	{
		"C":"OTHR",
		"Y":2040,
		"N":1430.3,
	},
	{
		"C":"OTHR",
		"Y":2041,
		"N":1448.0,
	},
	{
		"C":"OTHR",
		"Y":2042,
		"N":1465.5,
	},
	{
		"C":"OTHR",
		"Y":2043,
		"N":1481.7,
	},
	{
		"C":"OTHR",
		"Y":2044,
		"N":1498.7,
	},
	{
		"C":"OTHR",
		"Y":2045,
		"N":1515.1,
	},
	{
		"C":"OTHR",
		"Y":2046,
		"N":1531.6000000000001,
	},
	{
		"C":"OTHR",
		"Y":2047,
		"N":1548.1,
	},
	{
		"C":"OTHR",
		"Y":2048,
		"N":1562.7,
	},
	{
		"C":"OTHR",
		"Y":2049,
		"N":1579.8,
	},
	{
		"C":"OTHR",
		"Y":2050,
		"N":1593.8,
	},
	{
		"C":"TPCL",
		"Y":2019,
		"N":2512.53,
	},
	{
		"C":"TPCL",
		"Y":2020,
		"N":2451.3,
	},
	{
		"C":"TPCL",
		"Y":2021,
		"N":2591.2000000000003,
	},
	{
		"C":"TPCL",
		"Y":2022,
		"N":2655.9,
	},
	{
		"C":"TPCL",
		"Y":2023,
		"N":2715.0,
	},
	{
		"C":"TPCL",
		"Y":2024,
		"N":1804.0,
	},
	{
		"C":"TPCL",
		"Y":2025,
		"N":2784.3,
	},
	{
		"C":"TPCL",
		"Y":2026,
		"N":2809.2,
	},
	{
		"C":"TPCL",
		"Y":2027,
		"N":2829.5,
	},
	{
		"C":"TPCL",
		"Y":2028,
		"N":2855.6,
	},
	{
		"C":"TPCL",
		"Y":2029,
		"N":2888.0,
	},
	{
		"C":"TPCL",
		"Y":2030,
		"N":2917.1,
	},
	{
		"C":"TPCL",
		"Y":2031,
		"N":2936.6,
	},
	{
		"C":"TPCL",
		"Y":2032,
		"N":2963.7,
	},
	{
		"C":"TPCL",
		"Y":2033,
		"N":2990.0,
	},
	{
		"C":"TPCL",
		"Y":2034,
		"N":3021.7000000000003,
	},
	{
		"C":"TPCL",
		"Y":2035,
		"N":3046.6,
	},
	{
		"C":"TPCL",
		"Y":2036,
		"N":3072.1,
	},
	{
		"C":"TPCL",
		"Y":2037,
		"N":3098.3,
	},
	{
		"C":"TPCL",
		"Y":2038,
		"N":3121.5,
	},
	{
		"C":"TPCL",
		"Y":2039,
		"N":3144.6,
	},
	{
		"C":"TPCL",
		"Y":2040,
		"N":3169.4,
	},
	{
		"C":"TPCL",
		"Y":2041,
		"N":3191.3,
	},
	{
		"C":"TPCL",
		"Y":2042,
		"N":3216.6,
	},
	{
		"C":"TPCL",
		"Y":2043,
		"N":3240.2,
	},
	{
		"C":"TPCL",
		"Y":2044,
		"N":3262.9,
	},
	{
		"C":"TPCL",
		"Y":2045,
		"N":3287.2000000000003,
	},
	{
		"C":"TPCL",
		"Y":2046,
		"N":3308.0,
	},
	{
		"C":"TPCL",
		"Y":2047,
		"N":3327.4,
	},
	{
		"C":"TPCL",
		"Y":2048,
		"N":3344.0,
	},
	{
		"C":"TPCL",
		"Y":2049,
		"N":3363.4,
	},
	{
		"C":"TPCL",
		"Y":2050,
		"N":3376.8,
	},
	{
		"C":"HJI",
		"Y":2019,
		"N":6491.1,
	},
	{
		"C":"HJI",
		"Y":2020,
		"N":6505.9800000000005,
	},
	{
		"C":"HJI",
		"Y":2021,
		"N":6751.72,
	},
	{
		"C":"HJI",
		"Y":2022,
		"N":6921.54,
	},
	{
		"C":"HJI",
		"Y":2023,
		"N":7091.34,
	},
	{
		"C":"HJI",
		"Y":2024,
		"N":6072.5199999999995,
	},
	{
		"C":"HJI",
		"Y":2025,
		"N":7381.86,
	},
	{
		"C":"HJI",
		"Y":2026,
		"N":7512.06,
	},
	{
		"C":"HJI",
		"Y":2027,
		"N":7632.98,
	},
	{
		"C":"HJI",
		"Y":2028,
		"N":7750.34,
	},
	{
		"C":"HJI",
		"Y":2029,
		"N":7870.04,
	},
	{
		"C":"HJI",
		"Y":2030,
		"N":7983.02,
	},
	{
		"C":"HJI",
		"Y":2031,
		"N":8085.5,
	},
	{
		"C":"HJI",
		"Y":2032,
		"N":8195.58,
	},
	{
		"C":"HJI",
		"Y":2033,
		"N":8305.94,
	},
	{
		"C":"HJI",
		"Y":2034,
		"N":8418.82,
	},
	{
		"C":"HJI",
		"Y":2035,
		"N":8524.18,
	},
	{
		"C":"HJI",
		"Y":2036,
		"N":8630.14,
	},
	{
		"C":"HJI",
		"Y":2037,
		"N":8734.460000000001,
	},
	{
		"C":"HJI",
		"Y":2038,
		"N":8834.34,
	},
	{
		"C":"HJI",
		"Y":2039,
		"N":8932.32,
	},
	{
		"C":"HJI",
		"Y":2040,
		"N":9025.7,
	},
	{
		"C":"HJI",
		"Y":2041,
		"N":9196.64,
	},
	{
		"C":"HJI",
		"Y":2042,
		"N":9366.3,
	},
	{
		"C":"HJI",
		"Y":2043,
		"N":9528.5,
	},
	{
		"C":"HJI",
		"Y":2044,
		"N":9688.0,
	},
	{
		"C":"HJI",
		"Y":2045,
		"N":9848.02,
	},
	{
		"C":"HJI",
		"Y":2046,
		"N":10000.94,
	},
	{
		"C":"HJI",
		"Y":2047,
		"N":10151.92,
	},
	{
		"C":"HJI",
		"Y":2048,
		"N":10296.32,
	},
	{
		"C":"HJI",
		"Y":2049,
		"N":10442.8,
	},
	{
		"C":"HJI",
		"Y":2050,
		"N":10580.58,
	}
]
