[
	{
		"C":"HH",
		"Y":2019,
		"N":639.0,
	},
	{
		"C":"HH",
		"Y":2020,
		"N":641.0,
	},
	{
		"C":"HH",
		"Y":2021,
		"N":645.17,
	},
	{
		"C":"HH",
		"Y":2022,
		"N":650.33,
	},
	{
		"C":"HH",
		"Y":2023,
		"N":653.17,
	},
	{
		"C":"HH",
		"Y":2024,
		"N":657.0,
	},
	{
		"C":"HH",
		"Y":2025,
		"N":658.33,
	},
	{
		"C":"HH",
		"Y":2026,
		"N":659.5,
	},
	{
		"C":"HH",
		"Y":2027,
		"N":661.33,
	},
	{
		"C":"HH",
		"Y":2028,
		"N":662.67,
	},
	{
		"C":"HH",
		"Y":2029,
		"N":664.67,
	},
	{
		"C":"HH",
		"Y":2030,
		"N":665.83,
	},
	{
		"C":"HH",
		"Y":2031,
		"N":667.0,
	},
	{
		"C":"HH",
		"Y":2032,
		"N":668.5,
	},
	{
		"C":"HH",
		"Y":2033,
		"N":669.67,
	},
	{
		"C":"HH",
		"Y":2034,
		"N":670.5,
	},
	{
		"C":"HH",
		"Y":2035,
		"N":673.67,
	},
	{
		"C":"HH",
		"Y":2036,
		"N":675.5,
	},
	{
		"C":"HH",
		"Y":2037,
		"N":677.33,
	},
	{
		"C":"HH",
		"Y":2038,
		"N":677.17,
	},
	{
		"C":"HH",
		"Y":2039,
		"N":679.33,
	},
	{
		"C":"HH",
		"Y":2040,
		"N":679.67,
	},
	{
		"C":"HH",
		"Y":2041,
		"N":680.17,
	},
	{
		"C":"HH",
		"Y":2042,
		"N":681.83,
	},
	{
		"C":"HH",
		"Y":2043,
		"N":682.67,
	},
	{
		"C":"HH",
		"Y":2044,
		"N":685.67,
	},
	{
		"C":"HH",
		"Y":2045,
		"N":687.83,
	},
	{
		"C":"HH",
		"Y":2046,
		"N":689.67,
	},
	{
		"C":"HH",
		"Y":2047,
		"N":692.33,
	},
	{
		"C":"HH",
		"Y":2048,
		"N":694.0,
	},
	{
		"C":"HH",
		"Y":2049,
		"N":695.5,
	},
	{
		"C":"HH",
		"Y":2050,
		"N":697.83,
	},
	{
		"C":"POP",
		"Y":2019,
		"N":1165.89,
	},
	{
		"C":"POP",
		"Y":2020,
		"N":1168.06,
	},
	{
		"C":"POP",
		"Y":2021,
		"N":1171.05,
	},
	{
		"C":"POP",
		"Y":2022,
		"N":1178.61,
	},
	{
		"C":"POP",
		"Y":2023,
		"N":1182.29,
	},
	{
		"C":"POP",
		"Y":2024,
		"N":1187.18,
	},
	{
		"C":"POP",
		"Y":2025,
		"N":1186.15,
	},
	{
		"C":"POP",
		"Y":2026,
		"N":1185.66,
	},
	{
		"C":"POP",
		"Y":2027,
		"N":1185.09,
	},
	{
		"C":"POP",
		"Y":2028,
		"N":1184.78,
	},
	{
		"C":"POP",
		"Y":2029,
		"N":1187.15,
	},
	{
		"C":"POP",
		"Y":2030,
		"N":1184.99,
	},
	{
		"C":"POP",
		"Y":2031,
		"N":1183.27,
	},
	{
		"C":"POP",
		"Y":2032,
		"N":1183.08,
	},
	{
		"C":"POP",
		"Y":2033,
		"N":1184.05,
	},
	{
		"C":"POP",
		"Y":2034,
		"N":1181.29,
	},
	{
		"C":"POP",
		"Y":2035,
		"N":1184.02,
	},
	{
		"C":"POP",
		"Y":2036,
		"N":1182.88,
	},
	{
		"C":"POP",
		"Y":2037,
		"N":1181.63,
	},
	{
		"C":"POP",
		"Y":2038,
		"N":1176.59,
	},
	{
		"C":"POP",
		"Y":2039,
		"N":1176.19,
	},
	{
		"C":"POP",
		"Y":2040,
		"N":1174.43,
	},
	{
		"C":"POP",
		"Y":2041,
		"N":1171.38,
	},
	{
		"C":"POP",
		"Y":2042,
		"N":1170.56,
	},
	{
		"C":"POP",
		"Y":2043,
		"N":1169.1,
	},
	{
		"C":"POP",
		"Y":2044,
		"N":1169.07,
	},
	{
		"C":"POP",
		"Y":2045,
		"N":1169.58,
	},
	{
		"C":"POP",
		"Y":2046,
		"N":1167.88,
	},
	{
		"C":"POP",
		"Y":2047,
		"N":1169.11,
	},
	{
		"C":"POP",
		"Y":2048,
		"N":1169.84,
	},
	{
		"C":"POP",
		"Y":2049,
		"N":1169.83,
	},
	{
		"C":"POP",
		"Y":2050,
		"N":1172.15,
	},
	{
		"C":"AEMP",
		"Y":2019,
		"N":1597.96,
	},
	{
		"C":"AEMP",
		"Y":2020,
		"N":1561.98,
	},
	{
		"C":"AEMP",
		"Y":2021,
		"N":1620.25,
	},
	{
		"C":"AEMP",
		"Y":2022,
		"N":1579.63,
	},
	{
		"C":"AEMP",
		"Y":2023,
		"N":1587.1,
	},
	{
		"C":"AEMP",
		"Y":2024,
		"N":1593.14,
	},
	{
		"C":"AEMP",
		"Y":2025,
		"N":1602.07,
	},
	{
		"C":"AEMP",
		"Y":2026,
		"N":1602.92,
	},
	{
		"C":"AEMP",
		"Y":2027,
		"N":1606.84,
	},
	{
		"C":"AEMP",
		"Y":2028,
		"N":1606.81,
	},
	{
		"C":"AEMP",
		"Y":2029,
		"N":1607.88,
	},
	{
		"C":"AEMP",
		"Y":2030,
		"N":1613.61,
	},
	{
		"C":"AEMP",
		"Y":2031,
		"N":1610.99,
	},
	{
		"C":"AEMP",
		"Y":2032,
		"N":1609.79,
	},
	{
		"C":"AEMP",
		"Y":2033,
		"N":1609.13,
	},
	{
		"C":"AEMP",
		"Y":2034,
		"N":1610.78,
	},
	{
		"C":"AEMP",
		"Y":2035,
		"N":1619.2,
	},
	{
		"C":"AEMP",
		"Y":2036,
		"N":1615.0,
	},
	{
		"C":"AEMP",
		"Y":2037,
		"N":1617.24,
	},
	{
		"C":"AEMP",
		"Y":2038,
		"N":1618.28,
	},
	{
		"C":"AEMP",
		"Y":2039,
		"N":1620.43,
	},
	{
		"C":"AEMP",
		"Y":2040,
		"N":1629.1,
	},
	{
		"C":"AEMP",
		"Y":2041,
		"N":1623.44,
	},
	{
		"C":"AEMP",
		"Y":2042,
		"N":1623.06,
	},
	{
		"C":"AEMP",
		"Y":2043,
		"N":1625.78,
	},
	{
		"C":"AEMP",
		"Y":2044,
		"N":1629.77,
	},
	{
		"C":"AEMP",
		"Y":2045,
		"N":1633.58,
	},
	{
		"C":"AEMP",
		"Y":2046,
		"N":1635.26,
	},
	{
		"C":"AEMP",
		"Y":2047,
		"N":1648.08,
	},
	{
		"C":"AEMP",
		"Y":2048,
		"N":1655.8,
	},
	{
		"C":"AEMP",
		"Y":2049,
		"N":1659.01,
	},
	{
		"C":"AEMP",
		"Y":2050,
		"N":1662.81,
	},
	{
		"C":"RTL",
		"Y":2019,
		"N":23.0,
	},
	{
		"C":"RTL",
		"Y":2020,
		"N":21.33,
	},
	{
		"C":"RTL",
		"Y":2021,
		"N":23.33,
	},
	{
		"C":"RTL",
		"Y":2022,
		"N":22.66,
	},
	{
		"C":"RTL",
		"Y":2023,
		"N":22.5,
	},
	{
		"C":"RTL",
		"Y":2024,
		"N":22.34,
	},
	{
		"C":"RTL",
		"Y":2025,
		"N":22.5,
	},
	{
		"C":"RTL",
		"Y":2026,
		"N":22.5,
	},
	{
		"C":"RTL",
		"Y":2027,
		"N":22.5,
	},
	{
		"C":"RTL",
		"Y":2028,
		"N":22.5,
	},
	{
		"C":"RTL",
		"Y":2029,
		"N":22.83,
	},
	{
		"C":"RTL",
		"Y":2030,
		"N":23.0,
	},
	{
		"C":"RTL",
		"Y":2031,
		"N":22.66,
	},
	{
		"C":"RTL",
		"Y":2032,
		"N":22.66,
	},
	{
		"C":"RTL",
		"Y":2033,
		"N":22.66,
	},
	{
		"C":"RTL",
		"Y":2034,
		"N":22.83,
	},
	{
		"C":"RTL",
		"Y":2035,
		"N":22.83,
	},
	{
		"C":"RTL",
		"Y":2036,
		"N":22.83,
	},
	{
		"C":"RTL",
		"Y":2037,
		"N":22.83,
	},
	{
		"C":"RTL",
		"Y":2038,
		"N":22.83,
	},
	{
		"C":"RTL",
		"Y":2039,
		"N":22.83,
	},
	{
		"C":"RTL",
		"Y":2040,
		"N":22.83,
	},
	{
		"C":"RTL",
		"Y":2041,
		"N":22.83,
	},
	{
		"C":"RTL",
		"Y":2042,
		"N":22.83,
	},
	{
		"C":"RTL",
		"Y":2043,
		"N":23.0,
	},
	{
		"C":"RTL",
		"Y":2044,
		"N":23.0,
	},
	{
		"C":"RTL",
		"Y":2045,
		"N":23.17,
	},
	{
		"C":"RTL",
		"Y":2046,
		"N":23.17,
	},
	{
		"C":"RTL",
		"Y":2047,
		"N":23.17,
	},
	{
		"C":"RTL",
		"Y":2048,
		"N":23.34,
	},
	{
		"C":"RTL",
		"Y":2049,
		"N":23.34,
	},
	{
		"C":"RTL",
		"Y":2050,
		"N":23.34,
	},
	{
		"C":"IND",
		"Y":2019,
		"N":2.0,
	},
	{
		"C":"IND",
		"Y":2020,
		"N":1.83,
	},
	{
		"C":"IND",
		"Y":2021,
		"N":1.83,
	},
	{
		"C":"IND",
		"Y":2022,
		"N":1.83,
	},
	{
		"C":"IND",
		"Y":2023,
		"N":1.83,
	},
	{
		"C":"IND",
		"Y":2024,
		"N":1.83,
	},
	{
		"C":"IND",
		"Y":2025,
		"N":1.83,
	},
	{
		"C":"IND",
		"Y":2026,
		"N":1.83,
	},
	{
		"C":"IND",
		"Y":2027,
		"N":1.83,
	},
	{
		"C":"IND",
		"Y":2028,
		"N":1.83,
	},
	{
		"C":"IND",
		"Y":2029,
		"N":1.83,
	},
	{
		"C":"IND",
		"Y":2030,
		"N":1.83,
	},
	{
		"C":"IND",
		"Y":2031,
		"N":1.83,
	},
	{
		"C":"IND",
		"Y":2032,
		"N":1.83,
	},
	{
		"C":"IND",
		"Y":2033,
		"N":1.83,
	},
	{
		"C":"IND",
		"Y":2034,
		"N":1.83,
	},
	{
		"C":"IND",
		"Y":2035,
		"N":1.83,
	},
	{
		"C":"IND",
		"Y":2036,
		"N":1.83,
	},
	{
		"C":"IND",
		"Y":2037,
		"N":1.83,
	},
	{
		"C":"IND",
		"Y":2038,
		"N":1.83,
	},
	{
		"C":"IND",
		"Y":2039,
		"N":1.83,
	},
	{
		"C":"IND",
		"Y":2040,
		"N":1.83,
	},
	{
		"C":"IND",
		"Y":2041,
		"N":1.83,
	},
	{
		"C":"IND",
		"Y":2042,
		"N":1.83,
	},
	{
		"C":"IND",
		"Y":2043,
		"N":1.83,
	},
	{
		"C":"IND",
		"Y":2044,
		"N":1.83,
	},
	{
		"C":"IND",
		"Y":2045,
		"N":1.83,
	},
	{
		"C":"IND",
		"Y":2046,
		"N":1.83,
	},
	{
		"C":"IND",
		"Y":2047,
		"N":1.83,
	},
	{
		"C":"IND",
		"Y":2048,
		"N":1.83,
	},
	{
		"C":"IND",
		"Y":2049,
		"N":1.83,
	},
	{
		"C":"IND",
		"Y":2050,
		"N":1.83,
	},
	{
		"C":"OTHR",
		"Y":2019,
		"N":1454.0,
	},
	{
		"C":"OTHR",
		"Y":2020,
		"N":1386.51,
	},
	{
		"C":"OTHR",
		"Y":2021,
		"N":1455.16,
	},
	{
		"C":"OTHR",
		"Y":2022,
		"N":1460.84,
	},
	{
		"C":"OTHR",
		"Y":2023,
		"N":1462.34,
	},
	{
		"C":"OTHR",
		"Y":2024,
		"N":1462.67,
	},
	{
		"C":"OTHR",
		"Y":2025,
		"N":1462.83,
	},
	{
		"C":"OTHR",
		"Y":2026,
		"N":1463.17,
	},
	{
		"C":"OTHR",
		"Y":2027,
		"N":1463.34,
	},
	{
		"C":"OTHR",
		"Y":2028,
		"N":1463.5,
	},
	{
		"C":"OTHR",
		"Y":2029,
		"N":1464.01,
	},
	{
		"C":"OTHR",
		"Y":2030,
		"N":1464.01,
	},
	{
		"C":"OTHR",
		"Y":2031,
		"N":1464.17,
	},
	{
		"C":"OTHR",
		"Y":2032,
		"N":1464.17,
	},
	{
		"C":"OTHR",
		"Y":2033,
		"N":1464.51,
	},
	{
		"C":"OTHR",
		"Y":2034,
		"N":1464.51,
	},
	{
		"C":"OTHR",
		"Y":2035,
		"N":1464.51,
	},
	{
		"C":"OTHR",
		"Y":2036,
		"N":1464.51,
	},
	{
		"C":"OTHR",
		"Y":2037,
		"N":1464.67,
	},
	{
		"C":"OTHR",
		"Y":2038,
		"N":1464.67,
	},
	{
		"C":"OTHR",
		"Y":2039,
		"N":1464.84,
	},
	{
		"C":"OTHR",
		"Y":2040,
		"N":1464.84,
	},
	{
		"C":"OTHR",
		"Y":2041,
		"N":1465.01,
	},
	{
		"C":"OTHR",
		"Y":2042,
		"N":1465.01,
	},
	{
		"C":"OTHR",
		"Y":2043,
		"N":1465.51,
	},
	{
		"C":"OTHR",
		"Y":2044,
		"N":1465.51,
	},
	{
		"C":"OTHR",
		"Y":2045,
		"N":1465.51,
	},
	{
		"C":"OTHR",
		"Y":2046,
		"N":1465.51,
	},
	{
		"C":"OTHR",
		"Y":2047,
		"N":1465.51,
	},
	{
		"C":"OTHR",
		"Y":2048,
		"N":1465.51,
	},
	{
		"C":"OTHR",
		"Y":2049,
		"N":1465.67,
	},
	{
		"C":"OTHR",
		"Y":2050,
		"N":1465.84,
	},
	{
		"C":"TPCL",
		"Y":2019,
		"N":1479.0,
	},
	{
		"C":"TPCL",
		"Y":2020,
		"N":1409.67,
	},
	{
		"C":"TPCL",
		"Y":2021,
		"N":1480.32,
	},
	{
		"C":"TPCL",
		"Y":2022,
		"N":1485.33,
	},
	{
		"C":"TPCL",
		"Y":2023,
		"N":1486.67,
	},
	{
		"C":"TPCL",
		"Y":2024,
		"N":1486.84,
	},
	{
		"C":"TPCL",
		"Y":2025,
		"N":1487.16,
	},
	{
		"C":"TPCL",
		"Y":2026,
		"N":1487.5,
	},
	{
		"C":"TPCL",
		"Y":2027,
		"N":1487.67,
	},
	{
		"C":"TPCL",
		"Y":2028,
		"N":1487.83,
	},
	{
		"C":"TPCL",
		"Y":2029,
		"N":1488.67,
	},
	{
		"C":"TPCL",
		"Y":2030,
		"N":1488.84,
	},
	{
		"C":"TPCL",
		"Y":2031,
		"N":1488.66,
	},
	{
		"C":"TPCL",
		"Y":2032,
		"N":1488.66,
	},
	{
		"C":"TPCL",
		"Y":2033,
		"N":1489.0,
	},
	{
		"C":"TPCL",
		"Y":2034,
		"N":1489.17,
	},
	{
		"C":"TPCL",
		"Y":2035,
		"N":1489.17,
	},
	{
		"C":"TPCL",
		"Y":2036,
		"N":1489.17,
	},
	{
		"C":"TPCL",
		"Y":2037,
		"N":1489.33,
	},
	{
		"C":"TPCL",
		"Y":2038,
		"N":1489.33,
	},
	{
		"C":"TPCL",
		"Y":2039,
		"N":1489.5,
	},
	{
		"C":"TPCL",
		"Y":2040,
		"N":1489.5,
	},
	{
		"C":"TPCL",
		"Y":2041,
		"N":1489.67,
	},
	{
		"C":"TPCL",
		"Y":2042,
		"N":1489.67,
	},
	{
		"C":"TPCL",
		"Y":2043,
		"N":1490.34,
	},
	{
		"C":"TPCL",
		"Y":2044,
		"N":1490.34,
	},
	{
		"C":"TPCL",
		"Y":2045,
		"N":1490.51,
	},
	{
		"C":"TPCL",
		"Y":2046,
		"N":1490.51,
	},
	{
		"C":"TPCL",
		"Y":2047,
		"N":1490.51,
	},
	{
		"C":"TPCL",
		"Y":2048,
		"N":1490.68,
	},
	{
		"C":"TPCL",
		"Y":2049,
		"N":1490.84,
	},
	{
		"C":"TPCL",
		"Y":2050,
		"N":1491.01,
	},
	{
		"C":"HJI",
		"Y":2019,
		"N":2629.2,
	},
	{
		"C":"HJI",
		"Y":2020,
		"N":2563.47,
	},
	{
		"C":"HJI",
		"Y":2021,
		"N":2641.63,
	},
	{
		"C":"HJI",
		"Y":2022,
		"N":2655.92,
	},
	{
		"C":"HJI",
		"Y":2023,
		"N":2662.38,
	},
	{
		"C":"HJI",
		"Y":2024,
		"N":2669.44,
	},
	{
		"C":"HJI",
		"Y":2025,
		"N":2672.15,
	},
	{
		"C":"HJI",
		"Y":2026,
		"N":2674.6,
	},
	{
		"C":"HJI",
		"Y":2027,
		"N":2678.06,
	},
	{
		"C":"HJI",
		"Y":2028,
		"N":2680.64,
	},
	{
		"C":"HJI",
		"Y":2029,
		"N":2685.08,
	},
	{
		"C":"HJI",
		"Y":2030,
		"N":2687.33,
	},
	{
		"C":"HJI",
		"Y":2031,
		"N":2689.26,
	},
	{
		"C":"HJI",
		"Y":2032,
		"N":2691.96,
	},
	{
		"C":"HJI",
		"Y":2033,
		"N":2694.41,
	},
	{
		"C":"HJI",
		"Y":2034,
		"N":2696.07,
	},
	{
		"C":"HJI",
		"Y":2035,
		"N":2701.78,
	},
	{
		"C":"HJI",
		"Y":2036,
		"N":2705.07,
	},
	{
		"C":"HJI",
		"Y":2037,
		"N":2708.52,
	},
	{
		"C":"HJI",
		"Y":2038,
		"N":2708.24,
	},
	{
		"C":"HJI",
		"Y":2039,
		"N":2712.29,
	},
	{
		"C":"HJI",
		"Y":2040,
		"N":2712.91,
	},
	{
		"C":"HJI",
		"Y":2041,
		"N":2713.98,
	},
	{
		"C":"HJI",
		"Y":2042,
		"N":2716.96,
	},
	{
		"C":"HJI",
		"Y":2043,
		"N":2719.15,
	},
	{
		"C":"HJI",
		"Y":2044,
		"N":2724.55,
	},
	{
		"C":"HJI",
		"Y":2045,
		"N":2728.6,
	},
	{
		"C":"HJI",
		"Y":2046,
		"N":2731.92,
	},
	{
		"C":"HJI",
		"Y":2047,
		"N":2736.7,
	},
	{
		"C":"HJI",
		"Y":2048,
		"N":2739.88,
	},
	{
		"C":"HJI",
		"Y":2049,
		"N":2742.74,
	},
	{
		"C":"HJI",
		"Y":2050,
		"N":2747.1,
	}
]
