[
	{
		"C":"HH",
		"Y":2019,
		"N":167.0,
		"O":123.0
	},
	{
		"C":"HH",
		"Y":2020,
		"N":169.0,
		"O":128.0
	},
	{
		"C":"HH",
		"Y":2021,
		"N":171.0,
		"O":133.0
	},
	{
		"C":"HH",
		"Y":2022,
		"N":171.0,
		"O":136.0
	},
	{
		"C":"HH",
		"Y":2023,
		"N":171.0,
		"O":141.0
	},
	{
		"C":"HH",
		"Y":2024,
		"N":172.0,
		"O":144.0
	},
	{
		"C":"HH",
		"Y":2025,
		"N":174.0,
		"O":147.0
	},
	{
		"C":"HH",
		"Y":2026,
		"N":175.0,
		"O":150.0
	},
	{
		"C":"HH",
		"Y":2027,
		"N":177.0,
		"O":153.0
	},
	{
		"C":"HH",
		"Y":2028,
		"N":177.0,
		"O":157.0
	},
	{
		"C":"HH",
		"Y":2029,
		"N":179.0,
		"O":159.0
	},
	{
		"C":"HH",
		"Y":2030,
		"N":180.0,
		"O":163.0
	},
	{
		"C":"HH",
		"Y":2031,
		"N":180.0,
		"O":167.0
	},
	{
		"C":"HH",
		"Y":2032,
		"N":181.0,
		"O":171.0
	},
	{
		"C":"HH",
		"Y":2033,
		"N":181.0,
		"O":173.0
	},
	{
		"C":"HH",
		"Y":2034,
		"N":185.0,
		"O":176.0
	},
	{
		"C":"HH",
		"Y":2035,
		"N":186.0,
		"O":181.0
	},
	{
		"C":"HH",
		"Y":2036,
		"N":186.0,
		"O":184.0
	},
	{
		"C":"HH",
		"Y":2037,
		"N":184.0,
		"O":187.0
	},
	{
		"C":"HH",
		"Y":2038,
		"N":188.0,
		"O":189.0
	},
	{
		"C":"HH",
		"Y":2039,
		"N":188.0,
		"O":192.0
	},
	{
		"C":"HH",
		"Y":2040,
		"N":191.0,
		"O":195.0
	},
	{
		"C":"HH",
		"Y":2041,
		"N":192.0,
		"O":197.0
	},
	{
		"C":"HH",
		"Y":2042,
		"N":200.0,
		"O":198.0
	},
	{
		"C":"HH",
		"Y":2043,
		"N":202.0,
		"O":200.0
	},
	{
		"C":"HH",
		"Y":2044,
		"N":203.0,
		"O":201.0
	},
	{
		"C":"HH",
		"Y":2045,
		"N":207.0,
		"O":203.0
	},
	{
		"C":"HH",
		"Y":2046,
		"N":209.0,
		"O":205.0
	},
	{
		"C":"HH",
		"Y":2047,
		"N":209.0,
		"O":206.0
	},
	{
		"C":"HH",
		"Y":2048,
		"N":219.0,
		"O":209.0
	},
	{
		"C":"HH",
		"Y":2049,
		"N":224.0,
		"O":210.0
	},
	{
		"C":"HH",
		"Y":2050,
		"N":224.0,
		"O":213.0
	},
	{
		"C":"POP",
		"Y":2019,
		"N":585.0,
		"O":354.0
	},
	{
		"C":"POP",
		"Y":2020,
		"N":593.0,
		"O":368.0
	},
	{
		"C":"POP",
		"Y":2021,
		"N":601.0,
		"O":379.0
	},
	{
		"C":"POP",
		"Y":2022,
		"N":598.0,
		"O":387.0
	},
	{
		"C":"POP",
		"Y":2023,
		"N":595.0,
		"O":397.0
	},
	{
		"C":"POP",
		"Y":2024,
		"N":595.0,
		"O":402.0
	},
	{
		"C":"POP",
		"Y":2025,
		"N":602.0,
		"O":406.0
	},
	{
		"C":"POP",
		"Y":2026,
		"N":603.0,
		"O":413.0
	},
	{
		"C":"POP",
		"Y":2027,
		"N":604.0,
		"O":420.0
	},
	{
		"C":"POP",
		"Y":2028,
		"N":601.0,
		"O":427.0
	},
	{
		"C":"POP",
		"Y":2029,
		"N":603.0,
		"O":431.0
	},
	{
		"C":"POP",
		"Y":2030,
		"N":601.0,
		"O":436.0
	},
	{
		"C":"POP",
		"Y":2031,
		"N":597.0,
		"O":447.0
	},
	{
		"C":"POP",
		"Y":2032,
		"N":596.0,
		"O":452.0
	},
	{
		"C":"POP",
		"Y":2033,
		"N":593.0,
		"O":457.0
	},
	{
		"C":"POP",
		"Y":2034,
		"N":605.0,
		"O":463.0
	},
	{
		"C":"POP",
		"Y":2035,
		"N":604.0,
		"O":470.0
	},
	{
		"C":"POP",
		"Y":2036,
		"N":601.0,
		"O":478.0
	},
	{
		"C":"POP",
		"Y":2037,
		"N":593.0,
		"O":484.0
	},
	{
		"C":"POP",
		"Y":2038,
		"N":599.0,
		"O":489.0
	},
	{
		"C":"POP",
		"Y":2039,
		"N":596.0,
		"O":497.0
	},
	{
		"C":"POP",
		"Y":2040,
		"N":604.0,
		"O":504.0
	},
	{
		"C":"POP",
		"Y":2041,
		"N":601.0,
		"O":506.0
	},
	{
		"C":"POP",
		"Y":2042,
		"N":625.0,
		"O":509.0
	},
	{
		"C":"POP",
		"Y":2043,
		"N":624.0,
		"O":513.0
	},
	{
		"C":"POP",
		"Y":2044,
		"N":623.0,
		"O":514.0
	},
	{
		"C":"POP",
		"Y":2045,
		"N":633.0,
		"O":517.0
	},
	{
		"C":"POP",
		"Y":2046,
		"N":634.0,
		"O":520.0
	},
	{
		"C":"POP",
		"Y":2047,
		"N":631.0,
		"O":523.0
	},
	{
		"C":"POP",
		"Y":2048,
		"N":650.0,
		"O":529.0
	},
	{
		"C":"POP",
		"Y":2049,
		"N":659.0,
		"O":533.0
	},
	{
		"C":"POP",
		"Y":2050,
		"N":656.0,
		"O":537.0
	},
	{
		"C":"AEMP",
		"Y":2019,
		"N":232.0,
		"O":103.0
	},
	{
		"C":"AEMP",
		"Y":2020,
		"N":165.0,
		"O":92.0
	},
	{
		"C":"AEMP",
		"Y":2021,
		"N":225.0,
		"O":105.0
	},
	{
		"C":"AEMP",
		"Y":2022,
		"N":248.0,
		"O":107.0
	},
	{
		"C":"AEMP",
		"Y":2023,
		"N":286.0,
		"O":101.0
	},
	{
		"C":"AEMP",
		"Y":2024,
		"N":315.0,
		"O":109.0
	},
	{
		"C":"AEMP",
		"Y":2025,
		"N":326.0,
		"O":121.0
	},
	{
		"C":"AEMP",
		"Y":2026,
		"N":357.0,
		"O":109.0
	},
	{
		"C":"AEMP",
		"Y":2027,
		"N":344.0,
		"O":130.0
	},
	{
		"C":"AEMP",
		"Y":2028,
		"N":351.0,
		"O":100.0
	},
	{
		"C":"AEMP",
		"Y":2029,
		"N":363.0,
		"O":114.0
	},
	{
		"C":"AEMP",
		"Y":2030,
		"N":367.0,
		"O":158.0
	},
	{
		"C":"AEMP",
		"Y":2031,
		"N":371.0,
		"O":116.0
	},
	{
		"C":"AEMP",
		"Y":2032,
		"N":375.0,
		"O":123.0
	},
	{
		"C":"AEMP",
		"Y":2033,
		"N":376.0,
		"O":139.0
	},
	{
		"C":"AEMP",
		"Y":2034,
		"N":405.0,
		"O":148.0
	},
	{
		"C":"AEMP",
		"Y":2035,
		"N":376.0,
		"O":117.0
	},
	{
		"C":"AEMP",
		"Y":2036,
		"N":378.0,
		"O":141.0
	},
	{
		"C":"AEMP",
		"Y":2037,
		"N":474.0,
		"O":117.0
	},
	{
		"C":"AEMP",
		"Y":2038,
		"N":411.0,
		"O":125.0
	},
	{
		"C":"AEMP",
		"Y":2039,
		"N":379.0,
		"O":122.0
	},
	{
		"C":"AEMP",
		"Y":2040,
		"N":380.0,
		"O":114.0
	},
	{
		"C":"AEMP",
		"Y":2041,
		"N":380.0,
		"O":134.0
	},
	{
		"C":"AEMP",
		"Y":2042,
		"N":413.0,
		"O":124.0
	},
	{
		"C":"AEMP",
		"Y":2043,
		"N":382.0,
		"O":106.0
	},
	{
		"C":"AEMP",
		"Y":2044,
		"N":383.0,
		"O":143.0
	},
	{
		"C":"AEMP",
		"Y":2045,
		"N":452.0,
		"O":117.0
	},
	{
		"C":"AEMP",
		"Y":2046,
		"N":383.0,
		"O":141.0
	},
	{
		"C":"AEMP",
		"Y":2047,
		"N":383.0,
		"O":140.0
	},
	{
		"C":"AEMP",
		"Y":2048,
		"N":606.0,
		"O":132.0
	},
	{
		"C":"AEMP",
		"Y":2049,
		"N":385.0,
		"O":132.0
	},
	{
		"C":"AEMP",
		"Y":2050,
		"N":415.0,
		"O":117.0
	},
	{
		"C":"RTL",
		"Y":2019,
		"N":14.0,
		"O":12.0
	},
	{
		"C":"RTL",
		"Y":2020,
		"N":14.0,
		"O":14.0
	},
	{
		"C":"RTL",
		"Y":2021,
		"N":16.0,
		"O":15.0
	},
	{
		"C":"RTL",
		"Y":2022,
		"N":19.0,
		"O":13.0
	},
	{
		"C":"RTL",
		"Y":2023,
		"N":36.0,
		"O":13.0
	},
	{
		"C":"RTL",
		"Y":2024,
		"N":54.0,
		"O":13.0
	},
	{
		"C":"RTL",
		"Y":2025,
		"N":56.0,
		"O":14.0
	},
	{
		"C":"RTL",
		"Y":2026,
		"N":58.0,
		"O":15.0
	},
	{
		"C":"RTL",
		"Y":2027,
		"N":59.0,
		"O":15.0
	},
	{
		"C":"RTL",
		"Y":2028,
		"N":60.0,
		"O":15.0
	},
	{
		"C":"RTL",
		"Y":2029,
		"N":60.0,
		"O":15.0
	},
	{
		"C":"RTL",
		"Y":2030,
		"N":60.0,
		"O":16.0
	},
	{
		"C":"RTL",
		"Y":2031,
		"N":60.0,
		"O":17.0
	},
	{
		"C":"RTL",
		"Y":2032,
		"N":60.0,
		"O":18.0
	},
	{
		"C":"RTL",
		"Y":2033,
		"N":59.0,
		"O":18.0
	},
	{
		"C":"RTL",
		"Y":2034,
		"N":59.0,
		"O":18.0
	},
	{
		"C":"RTL",
		"Y":2035,
		"N":59.0,
		"O":17.0
	},
	{
		"C":"RTL",
		"Y":2036,
		"N":60.0,
		"O":17.0
	},
	{
		"C":"RTL",
		"Y":2037,
		"N":60.0,
		"O":17.0
	},
	{
		"C":"RTL",
		"Y":2038,
		"N":61.0,
		"O":17.0
	},
	{
		"C":"RTL",
		"Y":2039,
		"N":61.0,
		"O":17.0
	},
	{
		"C":"RTL",
		"Y":2040,
		"N":62.0,
		"O":17.0
	},
	{
		"C":"RTL",
		"Y":2041,
		"N":62.0,
		"O":18.0
	},
	{
		"C":"RTL",
		"Y":2042,
		"N":63.0,
		"O":16.0
	},
	{
		"C":"RTL",
		"Y":2043,
		"N":64.0,
		"O":16.0
	},
	{
		"C":"RTL",
		"Y":2044,
		"N":65.0,
		"O":16.0
	},
	{
		"C":"RTL",
		"Y":2045,
		"N":66.0,
		"O":16.0
	},
	{
		"C":"RTL",
		"Y":2046,
		"N":66.0,
		"O":16.0
	},
	{
		"C":"RTL",
		"Y":2047,
		"N":66.0,
		"O":16.0
	},
	{
		"C":"RTL",
		"Y":2048,
		"N":66.0,
		"O":16.0
	},
	{
		"C":"RTL",
		"Y":2049,
		"N":66.0,
		"O":16.0
	},
	{
		"C":"RTL",
		"Y":2050,
		"N":66.0,
		"O":16.0
	},
	{
		"C":"IND",
		"Y":2019,
		"N":75.0,
		"O":0.0
	},
	{
		"C":"IND",
		"Y":2020,
		"N":68.0,
		"O":1.0
	},
	{
		"C":"IND",
		"Y":2021,
		"N":99.0,
		"O":1.0
	},
	{
		"C":"IND",
		"Y":2022,
		"N":131.0,
		"O":1.0
	},
	{
		"C":"IND",
		"Y":2023,
		"N":134.0,
		"O":1.0
	},
	{
		"C":"IND",
		"Y":2024,
		"N":135.0,
		"O":1.0
	},
	{
		"C":"IND",
		"Y":2025,
		"N":139.0,
		"O":1.0
	},
	{
		"C":"IND",
		"Y":2026,
		"N":146.0,
		"O":1.0
	},
	{
		"C":"IND",
		"Y":2027,
		"N":149.0,
		"O":1.0
	},
	{
		"C":"IND",
		"Y":2028,
		"N":153.0,
		"O":1.0
	},
	{
		"C":"IND",
		"Y":2029,
		"N":162.0,
		"O":1.0
	},
	{
		"C":"IND",
		"Y":2030,
		"N":166.0,
		"O":1.0
	},
	{
		"C":"IND",
		"Y":2031,
		"N":170.0,
		"O":1.0
	},
	{
		"C":"IND",
		"Y":2032,
		"N":174.0,
		"O":1.0
	},
	{
		"C":"IND",
		"Y":2033,
		"N":175.0,
		"O":1.0
	},
	{
		"C":"IND",
		"Y":2034,
		"N":176.0,
		"O":1.0
	},
	{
		"C":"IND",
		"Y":2035,
		"N":176.0,
		"O":1.0
	},
	{
		"C":"IND",
		"Y":2036,
		"N":176.0,
		"O":1.0
	},
	{
		"C":"IND",
		"Y":2037,
		"N":176.0,
		"O":1.0
	},
	{
		"C":"IND",
		"Y":2038,
		"N":176.0,
		"O":1.0
	},
	{
		"C":"IND",
		"Y":2039,
		"N":176.0,
		"O":1.0
	},
	{
		"C":"IND",
		"Y":2040,
		"N":176.0,
		"O":1.0
	},
	{
		"C":"IND",
		"Y":2041,
		"N":176.0,
		"O":1.0
	},
	{
		"C":"IND",
		"Y":2042,
		"N":176.0,
		"O":1.0
	},
	{
		"C":"IND",
		"Y":2043,
		"N":176.0,
		"O":1.0
	},
	{
		"C":"IND",
		"Y":2044,
		"N":176.0,
		"O":1.0
	},
	{
		"C":"IND",
		"Y":2045,
		"N":176.0,
		"O":1.0
	},
	{
		"C":"IND",
		"Y":2046,
		"N":176.0,
		"O":1.0
	},
	{
		"C":"IND",
		"Y":2047,
		"N":176.0,
		"O":1.0
	},
	{
		"C":"IND",
		"Y":2048,
		"N":176.0,
		"O":1.0
	},
	{
		"C":"IND",
		"Y":2049,
		"N":176.0,
		"O":1.0
	},
	{
		"C":"IND",
		"Y":2050,
		"N":175.0,
		"O":1.0
	},
	{
		"C":"OTHR",
		"Y":2019,
		"N":61.0,
		"O":48.0
	},
	{
		"C":"OTHR",
		"Y":2020,
		"N":60.0,
		"O":53.0
	},
	{
		"C":"OTHR",
		"Y":2021,
		"N":67.0,
		"O":55.0
	},
	{
		"C":"OTHR",
		"Y":2022,
		"N":83.0,
		"O":58.0
	},
	{
		"C":"OTHR",
		"Y":2023,
		"N":101.0,
		"O":59.0
	},
	{
		"C":"OTHR",
		"Y":2024,
		"N":110.0,
		"O":60.0
	},
	{
		"C":"OTHR",
		"Y":2025,
		"N":115.0,
		"O":61.0
	},
	{
		"C":"OTHR",
		"Y":2026,
		"N":120.0,
		"O":62.0
	},
	{
		"C":"OTHR",
		"Y":2027,
		"N":120.0,
		"O":62.0
	},
	{
		"C":"OTHR",
		"Y":2028,
		"N":122.0,
		"O":61.0
	},
	{
		"C":"OTHR",
		"Y":2029,
		"N":125.0,
		"O":61.0
	},
	{
		"C":"OTHR",
		"Y":2030,
		"N":125.0,
		"O":62.0
	},
	{
		"C":"OTHR",
		"Y":2031,
		"N":125.0,
		"O":65.0
	},
	{
		"C":"OTHR",
		"Y":2032,
		"N":125.0,
		"O":69.0
	},
	{
		"C":"OTHR",
		"Y":2033,
		"N":126.0,
		"O":69.0
	},
	{
		"C":"OTHR",
		"Y":2034,
		"N":126.0,
		"O":71.0
	},
	{
		"C":"OTHR",
		"Y":2035,
		"N":126.0,
		"O":70.0
	},
	{
		"C":"OTHR",
		"Y":2036,
		"N":127.0,
		"O":71.0
	},
	{
		"C":"OTHR",
		"Y":2037,
		"N":127.0,
		"O":72.0
	},
	{
		"C":"OTHR",
		"Y":2038,
		"N":127.0,
		"O":73.0
	},
	{
		"C":"OTHR",
		"Y":2039,
		"N":127.0,
		"O":73.0
	},
	{
		"C":"OTHR",
		"Y":2040,
		"N":127.0,
		"O":73.0
	},
	{
		"C":"OTHR",
		"Y":2041,
		"N":127.0,
		"O":74.0
	},
	{
		"C":"OTHR",
		"Y":2042,
		"N":127.0,
		"O":73.0
	},
	{
		"C":"OTHR",
		"Y":2043,
		"N":127.0,
		"O":73.0
	},
	{
		"C":"OTHR",
		"Y":2044,
		"N":127.0,
		"O":74.0
	},
	{
		"C":"OTHR",
		"Y":2045,
		"N":127.0,
		"O":74.0
	},
	{
		"C":"OTHR",
		"Y":2046,
		"N":127.0,
		"O":74.0
	},
	{
		"C":"OTHR",
		"Y":2047,
		"N":127.0,
		"O":75.0
	},
	{
		"C":"OTHR",
		"Y":2048,
		"N":127.0,
		"O":75.0
	},
	{
		"C":"OTHR",
		"Y":2049,
		"N":128.0,
		"O":76.0
	},
	{
		"C":"OTHR",
		"Y":2050,
		"N":128.0,
		"O":76.0
	},
	{
		"C":"TPCL",
		"Y":2019,
		"N":150.0,
		"O":60.0
	},
	{
		"C":"TPCL",
		"Y":2020,
		"N":142.0,
		"O":67.0
	},
	{
		"C":"TPCL",
		"Y":2021,
		"N":182.0,
		"O":70.0
	},
	{
		"C":"TPCL",
		"Y":2022,
		"N":233.0,
		"O":72.0
	},
	{
		"C":"TPCL",
		"Y":2023,
		"N":271.0,
		"O":73.0
	},
	{
		"C":"TPCL",
		"Y":2024,
		"N":299.0,
		"O":74.0
	},
	{
		"C":"TPCL",
		"Y":2025,
		"N":310.0,
		"O":76.0
	},
	{
		"C":"TPCL",
		"Y":2026,
		"N":324.0,
		"O":77.0
	},
	{
		"C":"TPCL",
		"Y":2027,
		"N":328.0,
		"O":78.0
	},
	{
		"C":"TPCL",
		"Y":2028,
		"N":335.0,
		"O":77.0
	},
	{
		"C":"TPCL",
		"Y":2029,
		"N":347.0,
		"O":77.0
	},
	{
		"C":"TPCL",
		"Y":2030,
		"N":351.0,
		"O":77.0
	},
	{
		"C":"TPCL",
		"Y":2031,
		"N":355.0,
		"O":83.0
	},
	{
		"C":"TPCL",
		"Y":2032,
		"N":359.0,
		"O":88.0
	},
	{
		"C":"TPCL",
		"Y":2033,
		"N":360.0,
		"O":88.0
	},
	{
		"C":"TPCL",
		"Y":2034,
		"N":361.0,
		"O":90.0
	},
	{
		"C":"TPCL",
		"Y":2035,
		"N":361.0,
		"O":87.0
	},
	{
		"C":"TPCL",
		"Y":2036,
		"N":363.0,
		"O":89.0
	},
	{
		"C":"TPCL",
		"Y":2037,
		"N":363.0,
		"O":90.0
	},
	{
		"C":"TPCL",
		"Y":2038,
		"N":364.0,
		"O":90.0
	},
	{
		"C":"TPCL",
		"Y":2039,
		"N":364.0,
		"O":91.0
	},
	{
		"C":"TPCL",
		"Y":2040,
		"N":365.0,
		"O":91.0
	},
	{
		"C":"TPCL",
		"Y":2041,
		"N":365.0,
		"O":92.0
	},
	{
		"C":"TPCL",
		"Y":2042,
		"N":366.0,
		"O":89.0
	},
	{
		"C":"TPCL",
		"Y":2043,
		"N":367.0,
		"O":90.0
	},
	{
		"C":"TPCL",
		"Y":2044,
		"N":368.0,
		"O":90.0
	},
	{
		"C":"TPCL",
		"Y":2045,
		"N":369.0,
		"O":90.0
	},
	{
		"C":"TPCL",
		"Y":2046,
		"N":369.0,
		"O":91.0
	},
	{
		"C":"TPCL",
		"Y":2047,
		"N":369.0,
		"O":91.0
	},
	{
		"C":"TPCL",
		"Y":2048,
		"N":369.0,
		"O":91.0
	},
	{
		"C":"TPCL",
		"Y":2049,
		"N":370.0,
		"O":92.0
	},
	{
		"C":"TPCL",
		"Y":2050,
		"N":369.0,
		"O":93.0
	},
	{
		"C":"HJI",
		"Y":2019,
		"N":451.0,
		"O":282.0
	},
	{
		"C":"HJI",
		"Y":2020,
		"N":446.0,
		"O":297.0
	},
	{
		"C":"HJI",
		"Y":2021,
		"N":490.0,
		"O":310.0
	},
	{
		"C":"HJI",
		"Y":2022,
		"N":541.0,
		"O":317.0
	},
	{
		"C":"HJI",
		"Y":2023,
		"N":579.0,
		"O":327.0
	},
	{
		"C":"HJI",
		"Y":2024,
		"N":609.0,
		"O":333.0
	},
	{
		"C":"HJI",
		"Y":2025,
		"N":623.0,
		"O":341.0
	},
	{
		"C":"HJI",
		"Y":2026,
		"N":639.0,
		"O":347.0
	},
	{
		"C":"HJI",
		"Y":2027,
		"N":647.0,
		"O":354.0
	},
	{
		"C":"HJI",
		"Y":2028,
		"N":654.0,
		"O":360.0
	},
	{
		"C":"HJI",
		"Y":2029,
		"N":669.0,
		"O":364.0
	},
	{
		"C":"HJI",
		"Y":2030,
		"N":675.0,
		"O":370.0
	},
	{
		"C":"HJI",
		"Y":2031,
		"N":679.0,
		"O":384.0
	},
	{
		"C":"HJI",
		"Y":2032,
		"N":685.0,
		"O":395.0
	},
	{
		"C":"HJI",
		"Y":2033,
		"N":686.0,
		"O":399.0
	},
	{
		"C":"HJI",
		"Y":2034,
		"N":694.0,
		"O":408.0
	},
	{
		"C":"HJI",
		"Y":2035,
		"N":696.0,
		"O":412.0
	},
	{
		"C":"HJI",
		"Y":2036,
		"N":698.0,
		"O":420.0
	},
	{
		"C":"HJI",
		"Y":2037,
		"N":694.0,
		"O":425.0
	},
	{
		"C":"HJI",
		"Y":2038,
		"N":702.0,
		"O":430.0
	},
	{
		"C":"HJI",
		"Y":2039,
		"N":702.0,
		"O":438.0
	},
	{
		"C":"HJI",
		"Y":2040,
		"N":709.0,
		"O":442.0
	},
	{
		"C":"HJI",
		"Y":2041,
		"N":711.0,
		"O":446.0
	},
	{
		"C":"HJI",
		"Y":2042,
		"N":726.0,
		"O":446.0
	},
	{
		"C":"HJI",
		"Y":2043,
		"N":731.0,
		"O":450.0
	},
	{
		"C":"HJI",
		"Y":2044,
		"N":733.0,
		"O":453.0
	},
	{
		"C":"HJI",
		"Y":2045,
		"N":742.0,
		"O":456.0
	},
	{
		"C":"HJI",
		"Y":2046,
		"N":745.0,
		"O":459.0
	},
	{
		"C":"HJI",
		"Y":2047,
		"N":745.0,
		"O":462.0
	},
	{
		"C":"HJI",
		"Y":2048,
		"N":763.0,
		"O":467.0
	},
	{
		"C":"HJI",
		"Y":2049,
		"N":773.0,
		"O":471.0
	},
	{
		"C":"HJI",
		"Y":2050,
		"N":772.0,
		"O":476.0
	}
]
