[
	{
		"C":"HH",
		"Y":2019,
		"N":2.0,
		"O":40.0
	},
	{
		"C":"HH",
		"Y":2020,
		"N":2.0,
		"O":55.0
	},
	{
		"C":"HH",
		"Y":2021,
		"N":2.0,
		"O":79.0
	},
	{
		"C":"HH",
		"Y":2022,
		"N":2.0,
		"O":93.0
	},
	{
		"C":"HH",
		"Y":2023,
		"N":2.0,
		"O":101.0
	},
	{
		"C":"HH",
		"Y":2024,
		"N":7.0,
		"O":143.0
	},
	{
		"C":"HH",
		"Y":2025,
		"N":11.0,
		"O":158.0
	},
	{
		"C":"HH",
		"Y":2026,
		"N":18.0,
		"O":175.0
	},
	{
		"C":"HH",
		"Y":2027,
		"N":37.0,
		"O":182.0
	},
	{
		"C":"HH",
		"Y":2028,
		"N":47.0,
		"O":183.0
	},
	{
		"C":"HH",
		"Y":2029,
		"N":56.0,
		"O":184.0
	},
	{
		"C":"HH",
		"Y":2030,
		"N":68.0,
		"O":203.0
	},
	{
		"C":"HH",
		"Y":2031,
		"N":85.0,
		"O":212.0
	},
	{
		"C":"HH",
		"Y":2032,
		"N":101.0,
		"O":266.0
	},
	{
		"C":"HH",
		"Y":2033,
		"N":120.0,
		"O":291.0
	},
	{
		"C":"HH",
		"Y":2034,
		"N":142.0,
		"O":331.0
	},
	{
		"C":"HH",
		"Y":2035,
		"N":166.0,
		"O":380.0
	},
	{
		"C":"HH",
		"Y":2036,
		"N":188.0,
		"O":408.0
	},
	{
		"C":"HH",
		"Y":2037,
		"N":208.0,
		"O":415.0
	},
	{
		"C":"HH",
		"Y":2038,
		"N":215.0,
		"O":421.0
	},
	{
		"C":"HH",
		"Y":2039,
		"N":234.0,
		"O":457.0
	},
	{
		"C":"HH",
		"Y":2040,
		"N":247.0,
		"O":502.0
	},
	{
		"C":"HH",
		"Y":2041,
		"N":265.0,
		"O":547.0
	},
	{
		"C":"HH",
		"Y":2042,
		"N":281.0,
		"O":585.0
	},
	{
		"C":"HH",
		"Y":2043,
		"N":293.0,
		"O":623.0
	},
	{
		"C":"HH",
		"Y":2044,
		"N":298.0,
		"O":629.0
	},
	{
		"C":"HH",
		"Y":2045,
		"N":319.0,
		"O":652.0
	},
	{
		"C":"HH",
		"Y":2046,
		"N":338.0,
		"O":690.0
	},
	{
		"C":"HH",
		"Y":2047,
		"N":346.0,
		"O":695.0
	},
	{
		"C":"HH",
		"Y":2048,
		"N":351.0,
		"O":710.0
	},
	{
		"C":"HH",
		"Y":2049,
		"N":356.0,
		"O":711.0
	},
	{
		"C":"HH",
		"Y":2050,
		"N":368.0,
		"O":708.0
	},
	{
		"C":"POP",
		"Y":2019,
		"N":5.0,
		"O":148.0
	},
	{
		"C":"POP",
		"Y":2020,
		"N":5.0,
		"O":193.0
	},
	{
		"C":"POP",
		"Y":2021,
		"N":5.0,
		"O":283.0
	},
	{
		"C":"POP",
		"Y":2022,
		"N":5.0,
		"O":330.0
	},
	{
		"C":"POP",
		"Y":2023,
		"N":5.0,
		"O":360.0
	},
	{
		"C":"POP",
		"Y":2024,
		"N":17.0,
		"O":511.0
	},
	{
		"C":"POP",
		"Y":2025,
		"N":30.0,
		"O":557.0
	},
	{
		"C":"POP",
		"Y":2026,
		"N":55.0,
		"O":618.0
	},
	{
		"C":"POP",
		"Y":2027,
		"N":109.0,
		"O":635.0
	},
	{
		"C":"POP",
		"Y":2028,
		"N":148.0,
		"O":637.0
	},
	{
		"C":"POP",
		"Y":2029,
		"N":184.0,
		"O":639.0
	},
	{
		"C":"POP",
		"Y":2030,
		"N":230.0,
		"O":700.0
	},
	{
		"C":"POP",
		"Y":2031,
		"N":283.0,
		"O":729.0
	},
	{
		"C":"POP",
		"Y":2032,
		"N":336.0,
		"O":900.0
	},
	{
		"C":"POP",
		"Y":2033,
		"N":388.0,
		"O":974.0
	},
	{
		"C":"POP",
		"Y":2034,
		"N":470.0,
		"O":1081.0
	},
	{
		"C":"POP",
		"Y":2035,
		"N":543.0,
		"O":1223.0
	},
	{
		"C":"POP",
		"Y":2036,
		"N":620.0,
		"O":1321.0
	},
	{
		"C":"POP",
		"Y":2037,
		"N":683.0,
		"O":1338.0
	},
	{
		"C":"POP",
		"Y":2038,
		"N":702.0,
		"O":1353.0
	},
	{
		"C":"POP",
		"Y":2039,
		"N":776.0,
		"O":1469.0
	},
	{
		"C":"POP",
		"Y":2040,
		"N":816.0,
		"O":1616.0
	},
	{
		"C":"POP",
		"Y":2041,
		"N":873.0,
		"O":1752.0
	},
	{
		"C":"POP",
		"Y":2042,
		"N":920.0,
		"O":1879.0
	},
	{
		"C":"POP",
		"Y":2043,
		"N":951.0,
		"O":1992.0
	},
	{
		"C":"POP",
		"Y":2044,
		"N":964.0,
		"O":2013.0
	},
	{
		"C":"POP",
		"Y":2045,
		"N":1024.0,
		"O":2066.0
	},
	{
		"C":"POP",
		"Y":2046,
		"N":1071.0,
		"O":2172.0
	},
	{
		"C":"POP",
		"Y":2047,
		"N":1091.0,
		"O":2179.0
	},
	{
		"C":"POP",
		"Y":2048,
		"N":1097.0,
		"O":2211.0
	},
	{
		"C":"POP",
		"Y":2049,
		"N":1113.0,
		"O":2209.0
	},
	{
		"C":"POP",
		"Y":2050,
		"N":1134.0,
		"O":2193.0
	},
	{
		"C":"AEMP",
		"Y":2019,
		"N":3.0,
		"O":2.0
	},
	{
		"C":"AEMP",
		"Y":2020,
		"N":4.0,
		"O":150.0
	},
	{
		"C":"AEMP",
		"Y":2021,
		"N":3.0,
		"O":42.0
	},
	{
		"C":"AEMP",
		"Y":2022,
		"N":3.0,
		"O":49.0
	},
	{
		"C":"AEMP",
		"Y":2023,
		"N":3.0,
		"O":305.0
	},
	{
		"C":"AEMP",
		"Y":2024,
		"N":64.0,
		"O":53.0
	},
	{
		"C":"AEMP",
		"Y":2025,
		"N":63.0,
		"O":120.0
	},
	{
		"C":"AEMP",
		"Y":2026,
		"N":4.0,
		"O":49.0
	},
	{
		"C":"AEMP",
		"Y":2027,
		"N":124.0,
		"O":17.0
	},
	{
		"C":"AEMP",
		"Y":2028,
		"N":86.0,
		"O":33.0
	},
	{
		"C":"AEMP",
		"Y":2029,
		"N":7.0,
		"O":198.0
	},
	{
		"C":"AEMP",
		"Y":2030,
		"N":93.0,
		"O":274.0
	},
	{
		"C":"AEMP",
		"Y":2031,
		"N":8.0,
		"O":339.0
	},
	{
		"C":"AEMP",
		"Y":2032,
		"N":143.0,
		"O":164.0
	},
	{
		"C":"AEMP",
		"Y":2033,
		"N":241.0,
		"O":279.0
	},
	{
		"C":"AEMP",
		"Y":2034,
		"N":91.0,
		"O":363.0
	},
	{
		"C":"AEMP",
		"Y":2035,
		"N":143.0,
		"O":177.0
	},
	{
		"C":"AEMP",
		"Y":2036,
		"N":96.0,
		"O":84.0
	},
	{
		"C":"AEMP",
		"Y":2037,
		"N":186.0,
		"O":127.0
	},
	{
		"C":"AEMP",
		"Y":2038,
		"N":15.0,
		"O":396.0
	},
	{
		"C":"AEMP",
		"Y":2039,
		"N":16.0,
		"O":361.0
	},
	{
		"C":"AEMP",
		"Y":2040,
		"N":105.0,
		"O":342.0
	},
	{
		"C":"AEMP",
		"Y":2041,
		"N":93.0,
		"O":358.0
	},
	{
		"C":"AEMP",
		"Y":2042,
		"N":106.0,
		"O":253.0
	},
	{
		"C":"AEMP",
		"Y":2043,
		"N":19.0,
		"O":130.0
	},
	{
		"C":"AEMP",
		"Y":2044,
		"N":19.0,
		"O":241.0
	},
	{
		"C":"AEMP",
		"Y":2045,
		"N":315.0,
		"O":280.0
	},
	{
		"C":"AEMP",
		"Y":2046,
		"N":21.0,
		"O":143.0
	},
	{
		"C":"AEMP",
		"Y":2047,
		"N":22.0,
		"O":335.0
	},
	{
		"C":"AEMP",
		"Y":2048,
		"N":22.0,
		"O":348.0
	},
	{
		"C":"AEMP",
		"Y":2049,
		"N":33.0,
		"O":368.0
	},
	{
		"C":"AEMP",
		"Y":2050,
		"N":121.0,
		"O":361.0
	},
	{
		"C":"RTL",
		"Y":2019,
		"N":0.0,
		"O":0.0
	},
	{
		"C":"RTL",
		"Y":2020,
		"N":0.0,
		"O":0.0
	},
	{
		"C":"RTL",
		"Y":2021,
		"N":0.0,
		"O":0.0
	},
	{
		"C":"RTL",
		"Y":2022,
		"N":0.0,
		"O":0.0
	},
	{
		"C":"RTL",
		"Y":2023,
		"N":0.0,
		"O":0.0
	},
	{
		"C":"RTL",
		"Y":2024,
		"N":0.0,
		"O":0.0
	},
	{
		"C":"RTL",
		"Y":2025,
		"N":0.0,
		"O":0.0
	},
	{
		"C":"RTL",
		"Y":2026,
		"N":0.0,
		"O":0.0
	},
	{
		"C":"RTL",
		"Y":2027,
		"N":0.0,
		"O":0.0
	},
	{
		"C":"RTL",
		"Y":2028,
		"N":0.0,
		"O":0.0
	},
	{
		"C":"RTL",
		"Y":2029,
		"N":0.0,
		"O":0.0
	},
	{
		"C":"RTL",
		"Y":2030,
		"N":0.0,
		"O":0.0
	},
	{
		"C":"RTL",
		"Y":2031,
		"N":0.0,
		"O":0.0
	},
	{
		"C":"RTL",
		"Y":2032,
		"N":0.0,
		"O":0.0
	},
	{
		"C":"RTL",
		"Y":2033,
		"N":0.0,
		"O":0.0
	},
	{
		"C":"RTL",
		"Y":2034,
		"N":0.0,
		"O":0.0
	},
	{
		"C":"RTL",
		"Y":2035,
		"N":0.0,
		"O":1.0
	},
	{
		"C":"RTL",
		"Y":2036,
		"N":0.0,
		"O":1.0
	},
	{
		"C":"RTL",
		"Y":2037,
		"N":0.0,
		"O":1.0
	},
	{
		"C":"RTL",
		"Y":2038,
		"N":0.0,
		"O":1.0
	},
	{
		"C":"RTL",
		"Y":2039,
		"N":0.0,
		"O":1.0
	},
	{
		"C":"RTL",
		"Y":2040,
		"N":0.0,
		"O":1.0
	},
	{
		"C":"RTL",
		"Y":2041,
		"N":0.0,
		"O":1.0
	},
	{
		"C":"RTL",
		"Y":2042,
		"N":0.0,
		"O":1.0
	},
	{
		"C":"RTL",
		"Y":2043,
		"N":0.0,
		"O":1.0
	},
	{
		"C":"RTL",
		"Y":2044,
		"N":0.0,
		"O":1.0
	},
	{
		"C":"RTL",
		"Y":2045,
		"N":0.0,
		"O":1.0
	},
	{
		"C":"RTL",
		"Y":2046,
		"N":0.0,
		"O":1.0
	},
	{
		"C":"RTL",
		"Y":2047,
		"N":0.0,
		"O":1.0
	},
	{
		"C":"RTL",
		"Y":2048,
		"N":0.0,
		"O":4.0
	},
	{
		"C":"RTL",
		"Y":2049,
		"N":0.0,
		"O":6.0
	},
	{
		"C":"RTL",
		"Y":2050,
		"N":0.0,
		"O":5.0
	},
	{
		"C":"IND",
		"Y":2019,
		"N":0.0,
		"O":0.0
	},
	{
		"C":"IND",
		"Y":2020,
		"N":0.0,
		"O":0.0
	},
	{
		"C":"IND",
		"Y":2021,
		"N":0.0,
		"O":0.0
	},
	{
		"C":"IND",
		"Y":2022,
		"N":0.0,
		"O":0.0
	},
	{
		"C":"IND",
		"Y":2023,
		"N":0.0,
		"O":0.0
	},
	{
		"C":"IND",
		"Y":2024,
		"N":0.0,
		"O":0.0
	},
	{
		"C":"IND",
		"Y":2025,
		"N":0.0,
		"O":0.0
	},
	{
		"C":"IND",
		"Y":2026,
		"N":0.0,
		"O":0.0
	},
	{
		"C":"IND",
		"Y":2027,
		"N":0.0,
		"O":0.0
	},
	{
		"C":"IND",
		"Y":2028,
		"N":0.0,
		"O":0.0
	},
	{
		"C":"IND",
		"Y":2029,
		"N":0.0,
		"O":0.0
	},
	{
		"C":"IND",
		"Y":2030,
		"N":0.0,
		"O":0.0
	},
	{
		"C":"IND",
		"Y":2031,
		"N":0.0,
		"O":0.0
	},
	{
		"C":"IND",
		"Y":2032,
		"N":0.0,
		"O":0.0
	},
	{
		"C":"IND",
		"Y":2033,
		"N":0.0,
		"O":0.0
	},
	{
		"C":"IND",
		"Y":2034,
		"N":0.0,
		"O":0.0
	},
	{
		"C":"IND",
		"Y":2035,
		"N":0.0,
		"O":0.0
	},
	{
		"C":"IND",
		"Y":2036,
		"N":0.0,
		"O":0.0
	},
	{
		"C":"IND",
		"Y":2037,
		"N":0.0,
		"O":0.0
	},
	{
		"C":"IND",
		"Y":2038,
		"N":0.0,
		"O":0.0
	},
	{
		"C":"IND",
		"Y":2039,
		"N":0.0,
		"O":0.0
	},
	{
		"C":"IND",
		"Y":2040,
		"N":0.0,
		"O":0.0
	},
	{
		"C":"IND",
		"Y":2041,
		"N":0.0,
		"O":0.0
	},
	{
		"C":"IND",
		"Y":2042,
		"N":0.0,
		"O":0.0
	},
	{
		"C":"IND",
		"Y":2043,
		"N":0.0,
		"O":0.0
	},
	{
		"C":"IND",
		"Y":2044,
		"N":0.0,
		"O":0.0
	},
	{
		"C":"IND",
		"Y":2045,
		"N":0.0,
		"O":0.0
	},
	{
		"C":"IND",
		"Y":2046,
		"N":0.0,
		"O":0.0
	},
	{
		"C":"IND",
		"Y":2047,
		"N":0.0,
		"O":0.0
	},
	{
		"C":"IND",
		"Y":2048,
		"N":0.0,
		"O":0.0
	},
	{
		"C":"IND",
		"Y":2049,
		"N":0.0,
		"O":0.0
	},
	{
		"C":"IND",
		"Y":2050,
		"N":0.0,
		"O":0.0
	},
	{
		"C":"OTHR",
		"Y":2019,
		"N":0.0,
		"O":0.0
	},
	{
		"C":"OTHR",
		"Y":2020,
		"N":0.0,
		"O":0.0
	},
	{
		"C":"OTHR",
		"Y":2021,
		"N":0.0,
		"O":0.0
	},
	{
		"C":"OTHR",
		"Y":2022,
		"N":0.0,
		"O":0.0
	},
	{
		"C":"OTHR",
		"Y":2023,
		"N":0.0,
		"O":0.0
	},
	{
		"C":"OTHR",
		"Y":2024,
		"N":0.0,
		"O":0.0
	},
	{
		"C":"OTHR",
		"Y":2025,
		"N":0.0,
		"O":0.0
	},
	{
		"C":"OTHR",
		"Y":2026,
		"N":0.0,
		"O":0.0
	},
	{
		"C":"OTHR",
		"Y":2027,
		"N":0.0,
		"O":0.0
	},
	{
		"C":"OTHR",
		"Y":2028,
		"N":0.0,
		"O":0.0
	},
	{
		"C":"OTHR",
		"Y":2029,
		"N":0.0,
		"O":0.0
	},
	{
		"C":"OTHR",
		"Y":2030,
		"N":0.0,
		"O":0.0
	},
	{
		"C":"OTHR",
		"Y":2031,
		"N":0.0,
		"O":8.0
	},
	{
		"C":"OTHR",
		"Y":2032,
		"N":0.0,
		"O":16.0
	},
	{
		"C":"OTHR",
		"Y":2033,
		"N":0.0,
		"O":23.0
	},
	{
		"C":"OTHR",
		"Y":2034,
		"N":0.0,
		"O":30.0
	},
	{
		"C":"OTHR",
		"Y":2035,
		"N":0.0,
		"O":38.0
	},
	{
		"C":"OTHR",
		"Y":2036,
		"N":0.0,
		"O":47.0
	},
	{
		"C":"OTHR",
		"Y":2037,
		"N":0.0,
		"O":55.0
	},
	{
		"C":"OTHR",
		"Y":2038,
		"N":0.0,
		"O":61.0
	},
	{
		"C":"OTHR",
		"Y":2039,
		"N":0.0,
		"O":68.0
	},
	{
		"C":"OTHR",
		"Y":2040,
		"N":0.0,
		"O":71.0
	},
	{
		"C":"OTHR",
		"Y":2041,
		"N":0.0,
		"O":73.0
	},
	{
		"C":"OTHR",
		"Y":2042,
		"N":0.0,
		"O":76.0
	},
	{
		"C":"OTHR",
		"Y":2043,
		"N":0.0,
		"O":78.0
	},
	{
		"C":"OTHR",
		"Y":2044,
		"N":0.0,
		"O":80.0
	},
	{
		"C":"OTHR",
		"Y":2045,
		"N":0.0,
		"O":83.0
	},
	{
		"C":"OTHR",
		"Y":2046,
		"N":0.0,
		"O":86.0
	},
	{
		"C":"OTHR",
		"Y":2047,
		"N":0.0,
		"O":88.0
	},
	{
		"C":"OTHR",
		"Y":2048,
		"N":0.0,
		"O":287.0
	},
	{
		"C":"OTHR",
		"Y":2049,
		"N":0.0,
		"O":306.0
	},
	{
		"C":"OTHR",
		"Y":2050,
		"N":0.0,
		"O":297.0
	},
	{
		"C":"TPCL",
		"Y":2019,
		"N":0.0,
		"O":0.0
	},
	{
		"C":"TPCL",
		"Y":2020,
		"N":0.0,
		"O":0.0
	},
	{
		"C":"TPCL",
		"Y":2021,
		"N":0.0,
		"O":0.0
	},
	{
		"C":"TPCL",
		"Y":2022,
		"N":0.0,
		"O":0.0
	},
	{
		"C":"TPCL",
		"Y":2023,
		"N":0.0,
		"O":0.0
	},
	{
		"C":"TPCL",
		"Y":2024,
		"N":0.0,
		"O":0.0
	},
	{
		"C":"TPCL",
		"Y":2025,
		"N":0.0,
		"O":0.0
	},
	{
		"C":"TPCL",
		"Y":2026,
		"N":0.0,
		"O":0.0
	},
	{
		"C":"TPCL",
		"Y":2027,
		"N":0.0,
		"O":0.0
	},
	{
		"C":"TPCL",
		"Y":2028,
		"N":0.0,
		"O":0.0
	},
	{
		"C":"TPCL",
		"Y":2029,
		"N":0.0,
		"O":0.0
	},
	{
		"C":"TPCL",
		"Y":2030,
		"N":0.0,
		"O":0.0
	},
	{
		"C":"TPCL",
		"Y":2031,
		"N":0.0,
		"O":9.0
	},
	{
		"C":"TPCL",
		"Y":2032,
		"N":0.0,
		"O":16.0
	},
	{
		"C":"TPCL",
		"Y":2033,
		"N":0.0,
		"O":23.0
	},
	{
		"C":"TPCL",
		"Y":2034,
		"N":0.0,
		"O":31.0
	},
	{
		"C":"TPCL",
		"Y":2035,
		"N":0.0,
		"O":39.0
	},
	{
		"C":"TPCL",
		"Y":2036,
		"N":0.0,
		"O":48.0
	},
	{
		"C":"TPCL",
		"Y":2037,
		"N":0.0,
		"O":55.0
	},
	{
		"C":"TPCL",
		"Y":2038,
		"N":0.0,
		"O":62.0
	},
	{
		"C":"TPCL",
		"Y":2039,
		"N":0.0,
		"O":69.0
	},
	{
		"C":"TPCL",
		"Y":2040,
		"N":0.0,
		"O":72.0
	},
	{
		"C":"TPCL",
		"Y":2041,
		"N":0.0,
		"O":74.0
	},
	{
		"C":"TPCL",
		"Y":2042,
		"N":0.0,
		"O":77.0
	},
	{
		"C":"TPCL",
		"Y":2043,
		"N":0.0,
		"O":79.0
	},
	{
		"C":"TPCL",
		"Y":2044,
		"N":0.0,
		"O":81.0
	},
	{
		"C":"TPCL",
		"Y":2045,
		"N":0.0,
		"O":84.0
	},
	{
		"C":"TPCL",
		"Y":2046,
		"N":0.0,
		"O":87.0
	},
	{
		"C":"TPCL",
		"Y":2047,
		"N":0.0,
		"O":89.0
	},
	{
		"C":"TPCL",
		"Y":2048,
		"N":0.0,
		"O":292.0
	},
	{
		"C":"TPCL",
		"Y":2049,
		"N":0.0,
		"O":311.0
	},
	{
		"C":"TPCL",
		"Y":2050,
		"N":0.0,
		"O":302.0
	},
	{
		"C":"HJI",
		"Y":2019,
		"N":4.0,
		"O":73.0
	},
	{
		"C":"HJI",
		"Y":2020,
		"N":4.0,
		"O":99.0
	},
	{
		"C":"HJI",
		"Y":2021,
		"N":4.0,
		"O":142.0
	},
	{
		"C":"HJI",
		"Y":2022,
		"N":4.0,
		"O":168.0
	},
	{
		"C":"HJI",
		"Y":2023,
		"N":4.0,
		"O":182.0
	},
	{
		"C":"HJI",
		"Y":2024,
		"N":13.0,
		"O":258.0
	},
	{
		"C":"HJI",
		"Y":2025,
		"N":20.0,
		"O":284.0
	},
	{
		"C":"HJI",
		"Y":2026,
		"N":32.0,
		"O":315.0
	},
	{
		"C":"HJI",
		"Y":2027,
		"N":67.0,
		"O":327.0
	},
	{
		"C":"HJI",
		"Y":2028,
		"N":85.0,
		"O":329.0
	},
	{
		"C":"HJI",
		"Y":2029,
		"N":101.0,
		"O":330.0
	},
	{
		"C":"HJI",
		"Y":2030,
		"N":122.0,
		"O":365.0
	},
	{
		"C":"HJI",
		"Y":2031,
		"N":153.0,
		"O":391.0
	},
	{
		"C":"HJI",
		"Y":2032,
		"N":182.0,
		"O":495.0
	},
	{
		"C":"HJI",
		"Y":2033,
		"N":216.0,
		"O":547.0
	},
	{
		"C":"HJI",
		"Y":2034,
		"N":256.0,
		"O":626.0
	},
	{
		"C":"HJI",
		"Y":2035,
		"N":299.0,
		"O":722.0
	},
	{
		"C":"HJI",
		"Y":2036,
		"N":338.0,
		"O":783.0
	},
	{
		"C":"HJI",
		"Y":2037,
		"N":374.0,
		"O":802.0
	},
	{
		"C":"HJI",
		"Y":2038,
		"N":387.0,
		"O":819.0
	},
	{
		"C":"HJI",
		"Y":2039,
		"N":421.0,
		"O":892.0
	},
	{
		"C":"HJI",
		"Y":2040,
		"N":445.0,
		"O":975.0
	},
	{
		"C":"HJI",
		"Y":2041,
		"N":477.0,
		"O":1059.0
	},
	{
		"C":"HJI",
		"Y":2042,
		"N":506.0,
		"O":1131.0
	},
	{
		"C":"HJI",
		"Y":2043,
		"N":527.0,
		"O":1200.0
	},
	{
		"C":"HJI",
		"Y":2044,
		"N":536.0,
		"O":1214.0
	},
	{
		"C":"HJI",
		"Y":2045,
		"N":574.0,
		"O":1257.0
	},
	{
		"C":"HJI",
		"Y":2046,
		"N":608.0,
		"O":1329.0
	},
	{
		"C":"HJI",
		"Y":2047,
		"N":623.0,
		"O":1339.0
	},
	{
		"C":"HJI",
		"Y":2048,
		"N":632.0,
		"O":1570.0
	},
	{
		"C":"HJI",
		"Y":2049,
		"N":641.0,
		"O":1591.0
	},
	{
		"C":"HJI",
		"Y":2050,
		"N":662.0,
		"O":1577.0
	}
]
