[
	{
		"C":"HH",
		"Y":2019,
		"N":521.33,
	},
	{
		"C":"HH",
		"Y":2020,
		"N":527.0,
	},
	{
		"C":"HH",
		"Y":2021,
		"N":532.5,
	},
	{
		"C":"HH",
		"Y":2022,
		"N":536.83,
	},
	{
		"C":"HH",
		"Y":2023,
		"N":543.33,
	},
	{
		"C":"HH",
		"Y":2024,
		"N":547.83,
	},
	{
		"C":"HH",
		"Y":2025,
		"N":550.5,
	},
	{
		"C":"HH",
		"Y":2026,
		"N":554.17,
	},
	{
		"C":"HH",
		"Y":2027,
		"N":558.67,
	},
	{
		"C":"HH",
		"Y":2028,
		"N":563.33,
	},
	{
		"C":"HH",
		"Y":2029,
		"N":566.17,
	},
	{
		"C":"HH",
		"Y":2030,
		"N":569.33,
	},
	{
		"C":"HH",
		"Y":2031,
		"N":574.17,
	},
	{
		"C":"HH",
		"Y":2032,
		"N":578.5,
	},
	{
		"C":"HH",
		"Y":2033,
		"N":583.83,
	},
	{
		"C":"HH",
		"Y":2034,
		"N":587.67,
	},
	{
		"C":"HH",
		"Y":2035,
		"N":590.83,
	},
	{
		"C":"HH",
		"Y":2036,
		"N":593.83,
	},
	{
		"C":"HH",
		"Y":2037,
		"N":596.83,
	},
	{
		"C":"HH",
		"Y":2038,
		"N":601.17,
	},
	{
		"C":"HH",
		"Y":2039,
		"N":604.33,
	},
	{
		"C":"HH",
		"Y":2040,
		"N":606.33,
	},
	{
		"C":"HH",
		"Y":2041,
		"N":610.5,
	},
	{
		"C":"HH",
		"Y":2042,
		"N":613.67,
	},
	{
		"C":"HH",
		"Y":2043,
		"N":614.67,
	},
	{
		"C":"HH",
		"Y":2044,
		"N":616.67,
	},
	{
		"C":"HH",
		"Y":2045,
		"N":619.33,
	},
	{
		"C":"HH",
		"Y":2046,
		"N":621.5,
	},
	{
		"C":"HH",
		"Y":2047,
		"N":623.0,
	},
	{
		"C":"HH",
		"Y":2048,
		"N":624.67,
	},
	{
		"C":"HH",
		"Y":2049,
		"N":627.33,
	},
	{
		"C":"HH",
		"Y":2050,
		"N":629.67,
	},
	{
		"C":"POP",
		"Y":2019,
		"N":1074.87,
	},
	{
		"C":"POP",
		"Y":2020,
		"N":1089.88,
	},
	{
		"C":"POP",
		"Y":2021,
		"N":1096.04,
	},
	{
		"C":"POP",
		"Y":2022,
		"N":1102.88,
	},
	{
		"C":"POP",
		"Y":2023,
		"N":1114.31,
	},
	{
		"C":"POP",
		"Y":2024,
		"N":1120.89,
	},
	{
		"C":"POP",
		"Y":2025,
		"N":1122.66,
	},
	{
		"C":"POP",
		"Y":2026,
		"N":1125.67,
	},
	{
		"C":"POP",
		"Y":2027,
		"N":1129.34,
	},
	{
		"C":"POP",
		"Y":2028,
		"N":1135.68,
	},
	{
		"C":"POP",
		"Y":2029,
		"N":1135.7,
	},
	{
		"C":"POP",
		"Y":2030,
		"N":1138.02,
	},
	{
		"C":"POP",
		"Y":2031,
		"N":1142.64,
	},
	{
		"C":"POP",
		"Y":2032,
		"N":1148.88,
	},
	{
		"C":"POP",
		"Y":2033,
		"N":1156.66,
	},
	{
		"C":"POP",
		"Y":2034,
		"N":1159.33,
	},
	{
		"C":"POP",
		"Y":2035,
		"N":1160.25,
	},
	{
		"C":"POP",
		"Y":2036,
		"N":1161.11,
	},
	{
		"C":"POP",
		"Y":2037,
		"N":1163.49,
	},
	{
		"C":"POP",
		"Y":2038,
		"N":1168.32,
	},
	{
		"C":"POP",
		"Y":2039,
		"N":1173.03,
	},
	{
		"C":"POP",
		"Y":2040,
		"N":1172.3,
	},
	{
		"C":"POP",
		"Y":2041,
		"N":1172.91,
	},
	{
		"C":"POP",
		"Y":2042,
		"N":1173.26,
	},
	{
		"C":"POP",
		"Y":2043,
		"N":1170.8,
	},
	{
		"C":"POP",
		"Y":2044,
		"N":1170.94,
	},
	{
		"C":"POP",
		"Y":2045,
		"N":1171.62,
	},
	{
		"C":"POP",
		"Y":2046,
		"N":1172.69,
	},
	{
		"C":"POP",
		"Y":2047,
		"N":1171.35,
	},
	{
		"C":"POP",
		"Y":2048,
		"N":1171.45,
	},
	{
		"C":"POP",
		"Y":2049,
		"N":1172.96,
	},
	{
		"C":"POP",
		"Y":2050,
		"N":1173.67,
	},
	{
		"C":"AEMP",
		"Y":2019,
		"N":688.99,
	},
	{
		"C":"AEMP",
		"Y":2020,
		"N":697.45,
	},
	{
		"C":"AEMP",
		"Y":2021,
		"N":721.56,
	},
	{
		"C":"AEMP",
		"Y":2022,
		"N":707.82,
	},
	{
		"C":"AEMP",
		"Y":2023,
		"N":705.83,
	},
	{
		"C":"AEMP",
		"Y":2024,
		"N":710.14,
	},
	{
		"C":"AEMP",
		"Y":2025,
		"N":715.05,
	},
	{
		"C":"AEMP",
		"Y":2026,
		"N":716.03,
	},
	{
		"C":"AEMP",
		"Y":2027,
		"N":722.27,
	},
	{
		"C":"AEMP",
		"Y":2028,
		"N":720.5,
	},
	{
		"C":"AEMP",
		"Y":2029,
		"N":723.5,
	},
	{
		"C":"AEMP",
		"Y":2030,
		"N":725.9,
	},
	{
		"C":"AEMP",
		"Y":2031,
		"N":725.82,
	},
	{
		"C":"AEMP",
		"Y":2032,
		"N":728.53,
	},
	{
		"C":"AEMP",
		"Y":2033,
		"N":731.75,
	},
	{
		"C":"AEMP",
		"Y":2034,
		"N":726.6,
	},
	{
		"C":"AEMP",
		"Y":2035,
		"N":728.16,
	},
	{
		"C":"AEMP",
		"Y":2036,
		"N":727.85,
	},
	{
		"C":"AEMP",
		"Y":2037,
		"N":732.16,
	},
	{
		"C":"AEMP",
		"Y":2038,
		"N":730.21,
	},
	{
		"C":"AEMP",
		"Y":2039,
		"N":737.8,
	},
	{
		"C":"AEMP",
		"Y":2040,
		"N":739.44,
	},
	{
		"C":"AEMP",
		"Y":2041,
		"N":739.37,
	},
	{
		"C":"AEMP",
		"Y":2042,
		"N":744.19,
	},
	{
		"C":"AEMP",
		"Y":2043,
		"N":738.76,
	},
	{
		"C":"AEMP",
		"Y":2044,
		"N":740.29,
	},
	{
		"C":"AEMP",
		"Y":2045,
		"N":744.55,
	},
	{
		"C":"AEMP",
		"Y":2046,
		"N":746.11,
	},
	{
		"C":"AEMP",
		"Y":2047,
		"N":757.83,
	},
	{
		"C":"AEMP",
		"Y":2048,
		"N":761.9,
	},
	{
		"C":"AEMP",
		"Y":2049,
		"N":765.11,
	},
	{
		"C":"AEMP",
		"Y":2050,
		"N":771.24,
	},
	{
		"C":"RTL",
		"Y":2019,
		"N":49.0,
	},
	{
		"C":"RTL",
		"Y":2020,
		"N":46.67,
	},
	{
		"C":"RTL",
		"Y":2021,
		"N":49.84,
	},
	{
		"C":"RTL",
		"Y":2022,
		"N":48.0,
	},
	{
		"C":"RTL",
		"Y":2023,
		"N":47.0,
	},
	{
		"C":"RTL",
		"Y":2024,
		"N":46.0,
	},
	{
		"C":"RTL",
		"Y":2025,
		"N":45.5,
	},
	{
		"C":"RTL",
		"Y":2026,
		"N":45.5,
	},
	{
		"C":"RTL",
		"Y":2027,
		"N":45.5,
	},
	{
		"C":"RTL",
		"Y":2028,
		"N":45.5,
	},
	{
		"C":"RTL",
		"Y":2029,
		"N":45.5,
	},
	{
		"C":"RTL",
		"Y":2030,
		"N":45.5,
	},
	{
		"C":"RTL",
		"Y":2031,
		"N":45.5,
	},
	{
		"C":"RTL",
		"Y":2032,
		"N":46.0,
	},
	{
		"C":"RTL",
		"Y":2033,
		"N":46.5,
	},
	{
		"C":"RTL",
		"Y":2034,
		"N":47.0,
	},
	{
		"C":"RTL",
		"Y":2035,
		"N":47.33,
	},
	{
		"C":"RTL",
		"Y":2036,
		"N":47.33,
	},
	{
		"C":"RTL",
		"Y":2037,
		"N":47.5,
	},
	{
		"C":"RTL",
		"Y":2038,
		"N":47.67,
	},
	{
		"C":"RTL",
		"Y":2039,
		"N":47.67,
	},
	{
		"C":"RTL",
		"Y":2040,
		"N":47.83,
	},
	{
		"C":"RTL",
		"Y":2041,
		"N":48.17,
	},
	{
		"C":"RTL",
		"Y":2042,
		"N":48.33,
	},
	{
		"C":"RTL",
		"Y":2043,
		"N":48.83,
	},
	{
		"C":"RTL",
		"Y":2044,
		"N":49.17,
	},
	{
		"C":"RTL",
		"Y":2045,
		"N":49.5,
	},
	{
		"C":"RTL",
		"Y":2046,
		"N":49.67,
	},
	{
		"C":"RTL",
		"Y":2047,
		"N":50.34,
	},
	{
		"C":"RTL",
		"Y":2048,
		"N":50.84,
	},
	{
		"C":"RTL",
		"Y":2049,
		"N":51.0,
	},
	{
		"C":"RTL",
		"Y":2050,
		"N":51.17,
	},
	{
		"C":"IND",
		"Y":2019,
		"N":111.0,
	},
	{
		"C":"IND",
		"Y":2020,
		"N":110.5,
	},
	{
		"C":"IND",
		"Y":2021,
		"N":118.5,
	},
	{
		"C":"IND",
		"Y":2022,
		"N":120.83,
	},
	{
		"C":"IND",
		"Y":2023,
		"N":121.33,
	},
	{
		"C":"IND",
		"Y":2024,
		"N":121.5,
	},
	{
		"C":"IND",
		"Y":2025,
		"N":122.17,
	},
	{
		"C":"IND",
		"Y":2026,
		"N":122.34,
	},
	{
		"C":"IND",
		"Y":2027,
		"N":122.5,
	},
	{
		"C":"IND",
		"Y":2028,
		"N":122.67,
	},
	{
		"C":"IND",
		"Y":2029,
		"N":123.0,
	},
	{
		"C":"IND",
		"Y":2030,
		"N":123.17,
	},
	{
		"C":"IND",
		"Y":2031,
		"N":123.0,
	},
	{
		"C":"IND",
		"Y":2032,
		"N":123.0,
	},
	{
		"C":"IND",
		"Y":2033,
		"N":122.33,
	},
	{
		"C":"IND",
		"Y":2034,
		"N":122.16,
	},
	{
		"C":"IND",
		"Y":2035,
		"N":121.16,
	},
	{
		"C":"IND",
		"Y":2036,
		"N":121.0,
	},
	{
		"C":"IND",
		"Y":2037,
		"N":120.67,
	},
	{
		"C":"IND",
		"Y":2038,
		"N":119.5,
	},
	{
		"C":"IND",
		"Y":2039,
		"N":119.17,
	},
	{
		"C":"IND",
		"Y":2040,
		"N":118.17,
	},
	{
		"C":"IND",
		"Y":2041,
		"N":117.5,
	},
	{
		"C":"IND",
		"Y":2042,
		"N":117.33,
	},
	{
		"C":"IND",
		"Y":2043,
		"N":117.33,
	},
	{
		"C":"IND",
		"Y":2044,
		"N":117.0,
	},
	{
		"C":"IND",
		"Y":2045,
		"N":116.5,
	},
	{
		"C":"IND",
		"Y":2046,
		"N":116.33,
	},
	{
		"C":"IND",
		"Y":2047,
		"N":116.0,
	},
	{
		"C":"IND",
		"Y":2048,
		"N":115.5,
	},
	{
		"C":"IND",
		"Y":2049,
		"N":115.16,
	},
	{
		"C":"IND",
		"Y":2050,
		"N":114.17,
	},
	{
		"C":"OTHR",
		"Y":2019,
		"N":452.33,
	},
	{
		"C":"OTHR",
		"Y":2020,
		"N":429.16,
	},
	{
		"C":"OTHR",
		"Y":2021,
		"N":457.51,
	},
	{
		"C":"OTHR",
		"Y":2022,
		"N":466.34,
	},
	{
		"C":"OTHR",
		"Y":2023,
		"N":467.67,
	},
	{
		"C":"OTHR",
		"Y":2024,
		"N":468.83,
	},
	{
		"C":"OTHR",
		"Y":2025,
		"N":469.0,
	},
	{
		"C":"OTHR",
		"Y":2026,
		"N":469.33,
	},
	{
		"C":"OTHR",
		"Y":2027,
		"N":470.0,
	},
	{
		"C":"OTHR",
		"Y":2028,
		"N":470.33,
	},
	{
		"C":"OTHR",
		"Y":2029,
		"N":471.34,
	},
	{
		"C":"OTHR",
		"Y":2030,
		"N":471.67,
	},
	{
		"C":"OTHR",
		"Y":2031,
		"N":471.67,
	},
	{
		"C":"OTHR",
		"Y":2032,
		"N":472.84,
	},
	{
		"C":"OTHR",
		"Y":2033,
		"N":469.33,
	},
	{
		"C":"OTHR",
		"Y":2034,
		"N":470.17,
	},
	{
		"C":"OTHR",
		"Y":2035,
		"N":471.0,
	},
	{
		"C":"OTHR",
		"Y":2036,
		"N":471.68,
	},
	{
		"C":"OTHR",
		"Y":2037,
		"N":472.84,
	},
	{
		"C":"OTHR",
		"Y":2038,
		"N":473.84,
	},
	{
		"C":"OTHR",
		"Y":2039,
		"N":475.01,
	},
	{
		"C":"OTHR",
		"Y":2040,
		"N":475.67,
	},
	{
		"C":"OTHR",
		"Y":2041,
		"N":476.68,
	},
	{
		"C":"OTHR",
		"Y":2042,
		"N":474.51,
	},
	{
		"C":"OTHR",
		"Y":2043,
		"N":475.34,
	},
	{
		"C":"OTHR",
		"Y":2044,
		"N":476.51,
	},
	{
		"C":"OTHR",
		"Y":2045,
		"N":477.67,
	},
	{
		"C":"OTHR",
		"Y":2046,
		"N":478.67,
	},
	{
		"C":"OTHR",
		"Y":2047,
		"N":479.84,
	},
	{
		"C":"OTHR",
		"Y":2048,
		"N":481.34,
	},
	{
		"C":"OTHR",
		"Y":2049,
		"N":481.84,
	},
	{
		"C":"OTHR",
		"Y":2050,
		"N":478.68,
	},
	{
		"C":"TPCL",
		"Y":2019,
		"N":612.33,
	},
	{
		"C":"TPCL",
		"Y":2020,
		"N":586.33,
	},
	{
		"C":"TPCL",
		"Y":2021,
		"N":625.85,
	},
	{
		"C":"TPCL",
		"Y":2022,
		"N":635.17,
	},
	{
		"C":"TPCL",
		"Y":2023,
		"N":636.0,
	},
	{
		"C":"TPCL",
		"Y":2024,
		"N":636.33,
	},
	{
		"C":"TPCL",
		"Y":2025,
		"N":636.67,
	},
	{
		"C":"TPCL",
		"Y":2026,
		"N":637.17,
	},
	{
		"C":"TPCL",
		"Y":2027,
		"N":638.0,
	},
	{
		"C":"TPCL",
		"Y":2028,
		"N":638.5,
	},
	{
		"C":"TPCL",
		"Y":2029,
		"N":639.84,
	},
	{
		"C":"TPCL",
		"Y":2030,
		"N":640.34,
	},
	{
		"C":"TPCL",
		"Y":2031,
		"N":640.17,
	},
	{
		"C":"TPCL",
		"Y":2032,
		"N":641.84,
	},
	{
		"C":"TPCL",
		"Y":2033,
		"N":638.16,
	},
	{
		"C":"TPCL",
		"Y":2034,
		"N":639.33,
	},
	{
		"C":"TPCL",
		"Y":2035,
		"N":639.49,
	},
	{
		"C":"TPCL",
		"Y":2036,
		"N":640.01,
	},
	{
		"C":"TPCL",
		"Y":2037,
		"N":641.01,
	},
	{
		"C":"TPCL",
		"Y":2038,
		"N":641.01,
	},
	{
		"C":"TPCL",
		"Y":2039,
		"N":641.85,
	},
	{
		"C":"TPCL",
		"Y":2040,
		"N":641.67,
	},
	{
		"C":"TPCL",
		"Y":2041,
		"N":642.35,
	},
	{
		"C":"TPCL",
		"Y":2042,
		"N":640.17,
	},
	{
		"C":"TPCL",
		"Y":2043,
		"N":641.5,
	},
	{
		"C":"TPCL",
		"Y":2044,
		"N":642.68,
	},
	{
		"C":"TPCL",
		"Y":2045,
		"N":643.67,
	},
	{
		"C":"TPCL",
		"Y":2046,
		"N":644.67,
	},
	{
		"C":"TPCL",
		"Y":2047,
		"N":646.18,
	},
	{
		"C":"TPCL",
		"Y":2048,
		"N":647.68,
	},
	{
		"C":"TPCL",
		"Y":2049,
		"N":648.0,
	},
	{
		"C":"TPCL",
		"Y":2050,
		"N":644.02,
	},
	{
		"C":"HJI",
		"Y":2019,
		"N":1550.72,
	},
	{
		"C":"HJI",
		"Y":2020,
		"N":1534.93,
	},
	{
		"C":"HJI",
		"Y":2021,
		"N":1584.35,
	},
	{
		"C":"HJI",
		"Y":2022,
		"N":1601.46,
	},
	{
		"C":"HJI",
		"Y":2023,
		"N":1613.99,
	},
	{
		"C":"HJI",
		"Y":2024,
		"N":1622.42,
	},
	{
		"C":"HJI",
		"Y":2025,
		"N":1627.57,
	},
	{
		"C":"HJI",
		"Y":2026,
		"N":1634.68,
	},
	{
		"C":"HJI",
		"Y":2027,
		"N":1643.61,
	},
	{
		"C":"HJI",
		"Y":2028,
		"N":1652.49,
	},
	{
		"C":"HJI",
		"Y":2029,
		"N":1658.95,
	},
	{
		"C":"HJI",
		"Y":2030,
		"N":1665.13,
	},
	{
		"C":"HJI",
		"Y":2031,
		"N":1673.68,
	},
	{
		"C":"HJI",
		"Y":2032,
		"N":1683.14,
	},
	{
		"C":"HJI",
		"Y":2033,
		"N":1689.05,
	},
	{
		"C":"HJI",
		"Y":2034,
		"N":1697.14,
	},
	{
		"C":"HJI",
		"Y":2035,
		"N":1702.98,
	},
	{
		"C":"HJI",
		"Y":2036,
		"N":1708.9,
	},
	{
		"C":"HJI",
		"Y":2037,
		"N":1715.3,
	},
	{
		"C":"HJI",
		"Y":2038,
		"N":1723.12,
	},
	{
		"C":"HJI",
		"Y":2039,
		"N":1729.64,
	},
	{
		"C":"HJI",
		"Y":2040,
		"N":1733.06,
	},
	{
		"C":"HJI",
		"Y":2041,
		"N":1741.25,
	},
	{
		"C":"HJI",
		"Y":2042,
		"N":1744.78,
	},
	{
		"C":"HJI",
		"Y":2043,
		"N":1747.91,
	},
	{
		"C":"HJI",
		"Y":2044,
		"N":1752.69,
	},
	{
		"C":"HJI",
		"Y":2045,
		"N":1758.46,
	},
	{
		"C":"HJI",
		"Y":2046,
		"N":1763.37,
	},
	{
		"C":"HJI",
		"Y":2047,
		"N":1767.58,
	},
	{
		"C":"HJI",
		"Y":2048,
		"N":1772.09,
	},
	{
		"C":"HJI",
		"Y":2049,
		"N":1777.19,
	},
	{
		"C":"HJI",
		"Y":2050,
		"N":1777.43,
	}
]
