[
	{
		"C":"HH",
		"Y":2019,
		"N":2136.0,
		"O":2381.0
	},
	{
		"C":"HH",
		"Y":2020,
		"N":2225.0,
		"O":2394.0
	},
	{
		"C":"HH",
		"Y":2021,
		"N":2289.0,
		"O":2411.0
	},
	{
		"C":"HH",
		"Y":2022,
		"N":2328.0,
		"O":2422.0
	},
	{
		"C":"HH",
		"Y":2023,
		"N":2353.0,
		"O":2446.0
	},
	{
		"C":"HH",
		"Y":2024,
		"N":2364.0,
		"O":2464.0
	},
	{
		"C":"HH",
		"Y":2025,
		"N":2376.0,
		"O":2475.0
	},
	{
		"C":"HH",
		"Y":2026,
		"N":2385.0,
		"O":2491.0
	},
	{
		"C":"HH",
		"Y":2027,
		"N":2392.0,
		"O":2511.0
	},
	{
		"C":"HH",
		"Y":2028,
		"N":2397.0,
		"O":2525.0
	},
	{
		"C":"HH",
		"Y":2029,
		"N":2407.0,
		"O":2532.0
	},
	{
		"C":"HH",
		"Y":2030,
		"N":2415.0,
		"O":2549.0
	},
	{
		"C":"HH",
		"Y":2031,
		"N":2426.0,
		"O":2564.0
	},
	{
		"C":"HH",
		"Y":2032,
		"N":2429.0,
		"O":2579.0
	},
	{
		"C":"HH",
		"Y":2033,
		"N":2435.0,
		"O":2600.0
	},
	{
		"C":"HH",
		"Y":2034,
		"N":2444.0,
		"O":2615.0
	},
	{
		"C":"HH",
		"Y":2035,
		"N":2454.0,
		"O":2636.0
	},
	{
		"C":"HH",
		"Y":2036,
		"N":2458.0,
		"O":2660.0
	},
	{
		"C":"HH",
		"Y":2037,
		"N":2466.0,
		"O":2710.0
	},
	{
		"C":"HH",
		"Y":2038,
		"N":2490.0,
		"O":2771.0
	},
	{
		"C":"HH",
		"Y":2039,
		"N":2527.0,
		"O":2823.0
	},
	{
		"C":"HH",
		"Y":2040,
		"N":2564.0,
		"O":2876.0
	},
	{
		"C":"HH",
		"Y":2041,
		"N":2613.0,
		"O":2952.0
	},
	{
		"C":"HH",
		"Y":2042,
		"N":2642.0,
		"O":2997.0
	},
	{
		"C":"HH",
		"Y":2043,
		"N":2677.0,
		"O":3065.0
	},
	{
		"C":"HH",
		"Y":2044,
		"N":2699.0,
		"O":3147.0
	},
	{
		"C":"HH",
		"Y":2045,
		"N":2725.0,
		"O":3255.0
	},
	{
		"C":"HH",
		"Y":2046,
		"N":2743.0,
		"O":3347.0
	},
	{
		"C":"HH",
		"Y":2047,
		"N":2761.0,
		"O":3435.0
	},
	{
		"C":"HH",
		"Y":2048,
		"N":2774.0,
		"O":3555.0
	},
	{
		"C":"HH",
		"Y":2049,
		"N":2845.0,
		"O":3710.0
	},
	{
		"C":"HH",
		"Y":2050,
		"N":2918.0,
		"O":3857.0
	},
	{
		"C":"POP",
		"Y":2019,
		"N":5236.0,
		"O":6417.0
	},
	{
		"C":"POP",
		"Y":2020,
		"N":5528.0,
		"O":6454.0
	},
	{
		"C":"POP",
		"Y":2021,
		"N":5727.0,
		"O":6509.0
	},
	{
		"C":"POP",
		"Y":2022,
		"N":5853.0,
		"O":6547.0
	},
	{
		"C":"POP",
		"Y":2023,
		"N":5917.0,
		"O":6613.0
	},
	{
		"C":"POP",
		"Y":2024,
		"N":5956.0,
		"O":6670.0
	},
	{
		"C":"POP",
		"Y":2025,
		"N":5995.0,
		"O":6695.0
	},
	{
		"C":"POP",
		"Y":2026,
		"N":6015.0,
		"O":6736.0
	},
	{
		"C":"POP",
		"Y":2027,
		"N":6031.0,
		"O":6773.0
	},
	{
		"C":"POP",
		"Y":2028,
		"N":6050.0,
		"O":6818.0
	},
	{
		"C":"POP",
		"Y":2029,
		"N":6072.0,
		"O":6834.0
	},
	{
		"C":"POP",
		"Y":2030,
		"N":6097.0,
		"O":6877.0
	},
	{
		"C":"POP",
		"Y":2031,
		"N":6115.0,
		"O":6923.0
	},
	{
		"C":"POP",
		"Y":2032,
		"N":6126.0,
		"O":6959.0
	},
	{
		"C":"POP",
		"Y":2033,
		"N":6144.0,
		"O":7019.0
	},
	{
		"C":"POP",
		"Y":2034,
		"N":6165.0,
		"O":7057.0
	},
	{
		"C":"POP",
		"Y":2035,
		"N":6180.0,
		"O":7114.0
	},
	{
		"C":"POP",
		"Y":2036,
		"N":6196.0,
		"O":7175.0
	},
	{
		"C":"POP",
		"Y":2037,
		"N":6225.0,
		"O":7323.0
	},
	{
		"C":"POP",
		"Y":2038,
		"N":6286.0,
		"O":7494.0
	},
	{
		"C":"POP",
		"Y":2039,
		"N":6402.0,
		"O":7642.0
	},
	{
		"C":"POP",
		"Y":2040,
		"N":6517.0,
		"O":7783.0
	},
	{
		"C":"POP",
		"Y":2041,
		"N":6652.0,
		"O":7998.0
	},
	{
		"C":"POP",
		"Y":2042,
		"N":6767.0,
		"O":8122.0
	},
	{
		"C":"POP",
		"Y":2043,
		"N":6856.0,
		"O":8310.0
	},
	{
		"C":"POP",
		"Y":2044,
		"N":6921.0,
		"O":8554.0
	},
	{
		"C":"POP",
		"Y":2045,
		"N":7010.0,
		"O":8857.0
	},
	{
		"C":"POP",
		"Y":2046,
		"N":7065.0,
		"O":9097.0
	},
	{
		"C":"POP",
		"Y":2047,
		"N":7107.0,
		"O":9348.0
	},
	{
		"C":"POP",
		"Y":2048,
		"N":7143.0,
		"O":9659.0
	},
	{
		"C":"POP",
		"Y":2049,
		"N":7349.0,
		"O":10097.0
	},
	{
		"C":"POP",
		"Y":2050,
		"N":7559.0,
		"O":10497.0
	},
	{
		"C":"AEMP",
		"Y":2019,
		"N":8570.0,
		"O":5399.0
	},
	{
		"C":"AEMP",
		"Y":2020,
		"N":8218.0,
		"O":5493.0
	},
	{
		"C":"AEMP",
		"Y":2021,
		"N":8668.0,
		"O":5559.0
	},
	{
		"C":"AEMP",
		"Y":2022,
		"N":8767.0,
		"O":5638.0
	},
	{
		"C":"AEMP",
		"Y":2023,
		"N":8786.0,
		"O":5702.0
	},
	{
		"C":"AEMP",
		"Y":2024,
		"N":8797.0,
		"O":5756.0
	},
	{
		"C":"AEMP",
		"Y":2025,
		"N":8818.0,
		"O":5822.0
	},
	{
		"C":"AEMP",
		"Y":2026,
		"N":8841.0,
		"O":5878.0
	},
	{
		"C":"AEMP",
		"Y":2027,
		"N":8856.0,
		"O":5925.0
	},
	{
		"C":"AEMP",
		"Y":2028,
		"N":8881.0,
		"O":5959.0
	},
	{
		"C":"AEMP",
		"Y":2029,
		"N":8888.0,
		"O":5996.0
	},
	{
		"C":"AEMP",
		"Y":2030,
		"N":8899.0,
		"O":6052.0
	},
	{
		"C":"AEMP",
		"Y":2031,
		"N":8897.0,
		"O":6092.0
	},
	{
		"C":"AEMP",
		"Y":2032,
		"N":8926.0,
		"O":6122.0
	},
	{
		"C":"AEMP",
		"Y":2033,
		"N":8946.0,
		"O":6155.0
	},
	{
		"C":"AEMP",
		"Y":2034,
		"N":8978.0,
		"O":6184.0
	},
	{
		"C":"AEMP",
		"Y":2035,
		"N":8997.0,
		"O":6209.0
	},
	{
		"C":"AEMP",
		"Y":2036,
		"N":9029.0,
		"O":6260.0
	},
	{
		"C":"AEMP",
		"Y":2037,
		"N":9029.0,
		"O":6279.0
	},
	{
		"C":"AEMP",
		"Y":2038,
		"N":8993.0,
		"O":6284.0
	},
	{
		"C":"AEMP",
		"Y":2039,
		"N":8964.0,
		"O":6303.0
	},
	{
		"C":"AEMP",
		"Y":2040,
		"N":8954.0,
		"O":6317.0
	},
	{
		"C":"AEMP",
		"Y":2041,
		"N":8996.0,
		"O":6256.0
	},
	{
		"C":"AEMP",
		"Y":2042,
		"N":9033.0,
		"O":6173.0
	},
	{
		"C":"AEMP",
		"Y":2043,
		"N":9078.0,
		"O":6266.0
	},
	{
		"C":"AEMP",
		"Y":2044,
		"N":9111.0,
		"O":6287.0
	},
	{
		"C":"AEMP",
		"Y":2045,
		"N":9097.0,
		"O":6326.0
	},
	{
		"C":"AEMP",
		"Y":2046,
		"N":9105.0,
		"O":6360.0
	},
	{
		"C":"AEMP",
		"Y":2047,
		"N":9123.0,
		"O":6380.0
	},
	{
		"C":"AEMP",
		"Y":2048,
		"N":9133.0,
		"O":6354.0
	},
	{
		"C":"AEMP",
		"Y":2049,
		"N":8785.0,
		"O":6387.0
	},
	{
		"C":"AEMP",
		"Y":2050,
		"N":8744.0,
		"O":6344.0
	},
	{
		"C":"RTL",
		"Y":2019,
		"N":1766.0,
		"O":2238.0
	},
	{
		"C":"RTL",
		"Y":2020,
		"N":1672.0,
		"O":2241.0
	},
	{
		"C":"RTL",
		"Y":2021,
		"N":1705.0,
		"O":2242.0
	},
	{
		"C":"RTL",
		"Y":2022,
		"N":1652.0,
		"O":2245.0
	},
	{
		"C":"RTL",
		"Y":2023,
		"N":1625.0,
		"O":2247.0
	},
	{
		"C":"RTL",
		"Y":2024,
		"N":1595.0,
		"O":2247.0
	},
	{
		"C":"RTL",
		"Y":2025,
		"N":1590.0,
		"O":2252.0
	},
	{
		"C":"RTL",
		"Y":2026,
		"N":1591.0,
		"O":2255.0
	},
	{
		"C":"RTL",
		"Y":2027,
		"N":1592.0,
		"O":2261.0
	},
	{
		"C":"RTL",
		"Y":2028,
		"N":1593.0,
		"O":2266.0
	},
	{
		"C":"RTL",
		"Y":2029,
		"N":1594.0,
		"O":2266.0
	},
	{
		"C":"RTL",
		"Y":2030,
		"N":1597.0,
		"O":2270.0
	},
	{
		"C":"RTL",
		"Y":2031,
		"N":1593.0,
		"O":2270.0
	},
	{
		"C":"RTL",
		"Y":2032,
		"N":1611.0,
		"O":2272.0
	},
	{
		"C":"RTL",
		"Y":2033,
		"N":1624.0,
		"O":2273.0
	},
	{
		"C":"RTL",
		"Y":2034,
		"N":1638.0,
		"O":2275.0
	},
	{
		"C":"RTL",
		"Y":2035,
		"N":1649.0,
		"O":2275.0
	},
	{
		"C":"RTL",
		"Y":2036,
		"N":1660.0,
		"O":2275.0
	},
	{
		"C":"RTL",
		"Y":2037,
		"N":1675.0,
		"O":2246.0
	},
	{
		"C":"RTL",
		"Y":2038,
		"N":1698.0,
		"O":2240.0
	},
	{
		"C":"RTL",
		"Y":2039,
		"N":1736.0,
		"O":2237.0
	},
	{
		"C":"RTL",
		"Y":2040,
		"N":1759.0,
		"O":2232.0
	},
	{
		"C":"RTL",
		"Y":2041,
		"N":1790.0,
		"O":2232.0
	},
	{
		"C":"RTL",
		"Y":2042,
		"N":1803.0,
		"O":2153.0
	},
	{
		"C":"RTL",
		"Y":2043,
		"N":1826.0,
		"O":2190.0
	},
	{
		"C":"RTL",
		"Y":2044,
		"N":1838.0,
		"O":2212.0
	},
	{
		"C":"RTL",
		"Y":2045,
		"N":1844.0,
		"O":2209.0
	},
	{
		"C":"RTL",
		"Y":2046,
		"N":1854.0,
		"O":2218.0
	},
	{
		"C":"RTL",
		"Y":2047,
		"N":1866.0,
		"O":2226.0
	},
	{
		"C":"RTL",
		"Y":2048,
		"N":1873.0,
		"O":2231.0
	},
	{
		"C":"RTL",
		"Y":2049,
		"N":1811.0,
		"O":2238.0
	},
	{
		"C":"RTL",
		"Y":2050,
		"N":1791.0,
		"O":2244.0
	},
	{
		"C":"IND",
		"Y":2019,
		"N":1588.0,
		"O":743.0
	},
	{
		"C":"IND",
		"Y":2020,
		"N":1563.0,
		"O":771.0
	},
	{
		"C":"IND",
		"Y":2021,
		"N":1590.0,
		"O":795.0
	},
	{
		"C":"IND",
		"Y":2022,
		"N":1599.0,
		"O":808.0
	},
	{
		"C":"IND",
		"Y":2023,
		"N":1601.0,
		"O":815.0
	},
	{
		"C":"IND",
		"Y":2024,
		"N":1605.0,
		"O":830.0
	},
	{
		"C":"IND",
		"Y":2025,
		"N":1609.0,
		"O":840.0
	},
	{
		"C":"IND",
		"Y":2026,
		"N":1613.0,
		"O":845.0
	},
	{
		"C":"IND",
		"Y":2027,
		"N":1613.0,
		"O":849.0
	},
	{
		"C":"IND",
		"Y":2028,
		"N":1614.0,
		"O":851.0
	},
	{
		"C":"IND",
		"Y":2029,
		"N":1611.0,
		"O":854.0
	},
	{
		"C":"IND",
		"Y":2030,
		"N":1608.0,
		"O":858.0
	},
	{
		"C":"IND",
		"Y":2031,
		"N":1604.0,
		"O":860.0
	},
	{
		"C":"IND",
		"Y":2032,
		"N":1599.0,
		"O":864.0
	},
	{
		"C":"IND",
		"Y":2033,
		"N":1590.0,
		"O":867.0
	},
	{
		"C":"IND",
		"Y":2034,
		"N":1585.0,
		"O":869.0
	},
	{
		"C":"IND",
		"Y":2035,
		"N":1575.0,
		"O":870.0
	},
	{
		"C":"IND",
		"Y":2036,
		"N":1573.0,
		"O":871.0
	},
	{
		"C":"IND",
		"Y":2037,
		"N":1549.0,
		"O":871.0
	},
	{
		"C":"IND",
		"Y":2038,
		"N":1494.0,
		"O":873.0
	},
	{
		"C":"IND",
		"Y":2039,
		"N":1394.0,
		"O":870.0
	},
	{
		"C":"IND",
		"Y":2040,
		"N":1340.0,
		"O":871.0
	},
	{
		"C":"IND",
		"Y":2041,
		"N":1315.0,
		"O":870.0
	},
	{
		"C":"IND",
		"Y":2042,
		"N":1302.0,
		"O":847.0
	},
	{
		"C":"IND",
		"Y":2043,
		"N":1293.0,
		"O":847.0
	},
	{
		"C":"IND",
		"Y":2044,
		"N":1287.0,
		"O":839.0
	},
	{
		"C":"IND",
		"Y":2045,
		"N":1262.0,
		"O":839.0
	},
	{
		"C":"IND",
		"Y":2046,
		"N":1262.0,
		"O":839.0
	},
	{
		"C":"IND",
		"Y":2047,
		"N":1257.0,
		"O":832.0
	},
	{
		"C":"IND",
		"Y":2048,
		"N":1255.0,
		"O":831.0
	},
	{
		"C":"IND",
		"Y":2049,
		"N":1245.0,
		"O":832.0
	},
	{
		"C":"IND",
		"Y":2050,
		"N":1239.0,
		"O":833.0
	},
	{
		"C":"OTHR",
		"Y":2019,
		"N":5216.0,
		"O":2418.0
	},
	{
		"C":"OTHR",
		"Y":2020,
		"N":4983.0,
		"O":2481.0
	},
	{
		"C":"OTHR",
		"Y":2021,
		"N":5373.0,
		"O":2522.0
	},
	{
		"C":"OTHR",
		"Y":2022,
		"N":5516.0,
		"O":2585.0
	},
	{
		"C":"OTHR",
		"Y":2023,
		"N":5560.0,
		"O":2640.0
	},
	{
		"C":"OTHR",
		"Y":2024,
		"N":5597.0,
		"O":2679.0
	},
	{
		"C":"OTHR",
		"Y":2025,
		"N":5619.0,
		"O":2730.0
	},
	{
		"C":"OTHR",
		"Y":2026,
		"N":5637.0,
		"O":2778.0
	},
	{
		"C":"OTHR",
		"Y":2027,
		"N":5651.0,
		"O":2815.0
	},
	{
		"C":"OTHR",
		"Y":2028,
		"N":5674.0,
		"O":2842.0
	},
	{
		"C":"OTHR",
		"Y":2029,
		"N":5683.0,
		"O":2876.0
	},
	{
		"C":"OTHR",
		"Y":2030,
		"N":5694.0,
		"O":2924.0
	},
	{
		"C":"OTHR",
		"Y":2031,
		"N":5700.0,
		"O":2962.0
	},
	{
		"C":"OTHR",
		"Y":2032,
		"N":5716.0,
		"O":2986.0
	},
	{
		"C":"OTHR",
		"Y":2033,
		"N":5732.0,
		"O":3015.0
	},
	{
		"C":"OTHR",
		"Y":2034,
		"N":5755.0,
		"O":3040.0
	},
	{
		"C":"OTHR",
		"Y":2035,
		"N":5773.0,
		"O":3064.0
	},
	{
		"C":"OTHR",
		"Y":2036,
		"N":5796.0,
		"O":3114.0
	},
	{
		"C":"OTHR",
		"Y":2037,
		"N":5805.0,
		"O":3162.0
	},
	{
		"C":"OTHR",
		"Y":2038,
		"N":5801.0,
		"O":3171.0
	},
	{
		"C":"OTHR",
		"Y":2039,
		"N":5834.0,
		"O":3196.0
	},
	{
		"C":"OTHR",
		"Y":2040,
		"N":5855.0,
		"O":3214.0
	},
	{
		"C":"OTHR",
		"Y":2041,
		"N":5891.0,
		"O":3154.0
	},
	{
		"C":"OTHR",
		"Y":2042,
		"N":5928.0,
		"O":3173.0
	},
	{
		"C":"OTHR",
		"Y":2043,
		"N":5959.0,
		"O":3229.0
	},
	{
		"C":"OTHR",
		"Y":2044,
		"N":5986.0,
		"O":3236.0
	},
	{
		"C":"OTHR",
		"Y":2045,
		"N":5991.0,
		"O":3278.0
	},
	{
		"C":"OTHR",
		"Y":2046,
		"N":5989.0,
		"O":3303.0
	},
	{
		"C":"OTHR",
		"Y":2047,
		"N":6000.0,
		"O":3322.0
	},
	{
		"C":"OTHR",
		"Y":2048,
		"N":6005.0,
		"O":3292.0
	},
	{
		"C":"OTHR",
		"Y":2049,
		"N":5729.0,
		"O":3317.0
	},
	{
		"C":"OTHR",
		"Y":2050,
		"N":5714.0,
		"O":3267.0
	},
	{
		"C":"TPCL",
		"Y":2019,
		"N":8570.0,
		"O":5399.0
	},
	{
		"C":"TPCL",
		"Y":2020,
		"N":8218.0,
		"O":5493.0
	},
	{
		"C":"TPCL",
		"Y":2021,
		"N":8668.0,
		"O":5559.0
	},
	{
		"C":"TPCL",
		"Y":2022,
		"N":8767.0,
		"O":5638.0
	},
	{
		"C":"TPCL",
		"Y":2023,
		"N":8786.0,
		"O":5702.0
	},
	{
		"C":"TPCL",
		"Y":2024,
		"N":8797.0,
		"O":5756.0
	},
	{
		"C":"TPCL",
		"Y":2025,
		"N":8818.0,
		"O":5822.0
	},
	{
		"C":"TPCL",
		"Y":2026,
		"N":8841.0,
		"O":5878.0
	},
	{
		"C":"TPCL",
		"Y":2027,
		"N":8856.0,
		"O":5925.0
	},
	{
		"C":"TPCL",
		"Y":2028,
		"N":8881.0,
		"O":5959.0
	},
	{
		"C":"TPCL",
		"Y":2029,
		"N":8888.0,
		"O":5996.0
	},
	{
		"C":"TPCL",
		"Y":2030,
		"N":8899.0,
		"O":6052.0
	},
	{
		"C":"TPCL",
		"Y":2031,
		"N":8897.0,
		"O":6092.0
	},
	{
		"C":"TPCL",
		"Y":2032,
		"N":8926.0,
		"O":6122.0
	},
	{
		"C":"TPCL",
		"Y":2033,
		"N":8946.0,
		"O":6155.0
	},
	{
		"C":"TPCL",
		"Y":2034,
		"N":8978.0,
		"O":6184.0
	},
	{
		"C":"TPCL",
		"Y":2035,
		"N":8997.0,
		"O":6209.0
	},
	{
		"C":"TPCL",
		"Y":2036,
		"N":9029.0,
		"O":6260.0
	},
	{
		"C":"TPCL",
		"Y":2037,
		"N":9029.0,
		"O":6279.0
	},
	{
		"C":"TPCL",
		"Y":2038,
		"N":8993.0,
		"O":6284.0
	},
	{
		"C":"TPCL",
		"Y":2039,
		"N":8964.0,
		"O":6303.0
	},
	{
		"C":"TPCL",
		"Y":2040,
		"N":8954.0,
		"O":6317.0
	},
	{
		"C":"TPCL",
		"Y":2041,
		"N":8996.0,
		"O":6256.0
	},
	{
		"C":"TPCL",
		"Y":2042,
		"N":9033.0,
		"O":6173.0
	},
	{
		"C":"TPCL",
		"Y":2043,
		"N":9078.0,
		"O":6266.0
	},
	{
		"C":"TPCL",
		"Y":2044,
		"N":9111.0,
		"O":6287.0
	},
	{
		"C":"TPCL",
		"Y":2045,
		"N":9097.0,
		"O":6326.0
	},
	{
		"C":"TPCL",
		"Y":2046,
		"N":9105.0,
		"O":6360.0
	},
	{
		"C":"TPCL",
		"Y":2047,
		"N":9123.0,
		"O":6380.0
	},
	{
		"C":"TPCL",
		"Y":2048,
		"N":9133.0,
		"O":6354.0
	},
	{
		"C":"TPCL",
		"Y":2049,
		"N":8785.0,
		"O":6387.0
	},
	{
		"C":"TPCL",
		"Y":2050,
		"N":8744.0,
		"O":6344.0
	},
	{
		"C":"HJI",
		"Y":2019,
		"N":12415.0,
		"O":9685.0
	},
	{
		"C":"HJI",
		"Y":2020,
		"N":12223.0,
		"O":9802.0
	},
	{
		"C":"HJI",
		"Y":2021,
		"N":12788.0,
		"O":9899.0
	},
	{
		"C":"HJI",
		"Y":2022,
		"N":12957.0,
		"O":9998.0
	},
	{
		"C":"HJI",
		"Y":2023,
		"N":13021.0,
		"O":10105.0
	},
	{
		"C":"HJI",
		"Y":2024,
		"N":13052.0,
		"O":10191.0
	},
	{
		"C":"HJI",
		"Y":2025,
		"N":13095.0,
		"O":10277.0
	},
	{
		"C":"HJI",
		"Y":2026,
		"N":13134.0,
		"O":10362.0
	},
	{
		"C":"HJI",
		"Y":2027,
		"N":13162.0,
		"O":10445.0
	},
	{
		"C":"HJI",
		"Y":2028,
		"N":13196.0,
		"O":10504.0
	},
	{
		"C":"HJI",
		"Y":2029,
		"N":13221.0,
		"O":10554.0
	},
	{
		"C":"HJI",
		"Y":2030,
		"N":13246.0,
		"O":10640.0
	},
	{
		"C":"HJI",
		"Y":2031,
		"N":13264.0,
		"O":10707.0
	},
	{
		"C":"HJI",
		"Y":2032,
		"N":13298.0,
		"O":10764.0
	},
	{
		"C":"HJI",
		"Y":2033,
		"N":13329.0,
		"O":10835.0
	},
	{
		"C":"HJI",
		"Y":2034,
		"N":13377.0,
		"O":10891.0
	},
	{
		"C":"HJI",
		"Y":2035,
		"N":13414.0,
		"O":10954.0
	},
	{
		"C":"HJI",
		"Y":2036,
		"N":13453.0,
		"O":11048.0
	},
	{
		"C":"HJI",
		"Y":2037,
		"N":13468.0,
		"O":11157.0
	},
	{
		"C":"HJI",
		"Y":2038,
		"N":13475.0,
		"O":11272.0
	},
	{
		"C":"HJI",
		"Y":2039,
		"N":13513.0,
		"O":11384.0
	},
	{
		"C":"HJI",
		"Y":2040,
		"N":13569.0,
		"O":11494.0
	},
	{
		"C":"HJI",
		"Y":2041,
		"N":13699.0,
		"O":11570.0
	},
	{
		"C":"HJI",
		"Y":2042,
		"N":13789.0,
		"O":11568.0
	},
	{
		"C":"HJI",
		"Y":2043,
		"N":13897.0,
		"O":11783.0
	},
	{
		"C":"HJI",
		"Y":2044,
		"N":13969.0,
		"O":11952.0
	},
	{
		"C":"HJI",
		"Y":2045,
		"N":14002.0,
		"O":12185.0
	},
	{
		"C":"HJI",
		"Y":2046,
		"N":14042.0,
		"O":12385.0
	},
	{
		"C":"HJI",
		"Y":2047,
		"N":14093.0,
		"O":12563.0
	},
	{
		"C":"HJI",
		"Y":2048,
		"N":14126.0,
		"O":12753.0
	},
	{
		"C":"HJI",
		"Y":2049,
		"N":13906.0,
		"O":13065.0
	},
	{
		"C":"HJI",
		"Y":2050,
		"N":13996.0,
		"O":13287.0
	}
]
